Workbook

Sheet Summary
B2: Client Name - HOOPP (Healthcare of Ontario Pension Plan) | F2: Services Entitlements
B3: General Details | C3: Live Since | F3: Services | G3: Entitled | H3: Comments
C4: Client Time Zone | D4: EST | F4: Application Monitoring(AM) - PROD | G4: Yes
C5: Business Hrs. | D5: 8:00am to 5:00pm | F5: Business Assistance(BA) | G5: No
B6: Client Contact Details | C6: Mailing Group | D6: goldensourceoperations@hoopp.com | F6: Custom Configuration Management(CM) | G6: Yes
B8: Implementation Details | C8: Application Version | D8: 8.9.0
C9: Modules | D9: Security Master
D10: Price Master | F10: Workload Details IST
F11: Shift | G11: Timing | H11: Workload
C12: GoldenCopy | D12: Yes | F12: Night | G12: 12:00am to 04:00am | H12: High
C13: VDDB | D13: Yes | F13: Night-Morning | G13: 04:00am to 08:00am | H13: High
C14: DWH | D14: No | F14: Morning | G14: 08:00am to 12:00pm | H14: Low
C15: Insight | D15: Yes | F15: Morning-Afternoon | G15: 12:00pm to 04:00pm | H15: Low
C16: Talend | D16: No | F16: Afternoon | G16: 04:00pm to 08:00pm | H16: Low
C17: Scheduler | D17: Job Scheduler | F17: Afternoon-Night | G17: 08:00pm to 12:00am | H17: High
C18: Clustered | D18: No
C19: App. Server | D19: Jboss
C20: Queue Config | D20: No
B21: Vendor Details | C21: Bloomberg | D21: http://service.bloomberg.com Urgent issues: 1-212-617-4390 Global Technical Support: 1-212-318-2000
C22: Markit | D22: support@markit.com red@ihsmarkit.com CALL THIS NUMBER - GOES TO ALL INDIA SUPPORT STAFF: +91 120 611 8051 MK-ValHOOPP@ihsmarkit.com Kamal.Sehgal@ihsmarkit.com Vrinda.Pal@ihsmarkit.com Managers: Sachin.Singhal@ihsmarkit.com Rajesh.Kumar2@ihsmarkit.com Toronto Staff: spencer.wiseman@ihsmarkit.com Abhinit.Kumar@ihsmarkit.com
C23: S&P | D23: Product.Notification <Product.Notification@spglobal.com>
C24: FTSE | D24: PC-Bond Index Team <pcbond@FTSERussell.com> Always CC: Info@ftserussell.com Front Desk: Phone: 1-866-551-0617
C25: S&P Index | D25: Index_services@spdji.com index_services@spglobal.com Phone: 1-212-438-2046
C26: SVC | D26: dco@ssnc.com SVC-ClientSupport@sscinc.com Portch, Glenn <gportch@sscinc.com> Garito, Nick <ngarito@sscinc.com> Martinis, Peter pmartinis@sscinc.com call 905 629-8000 and choose prompt #1, then prompt #7 for SVC
C27: ICE | D27: icelinksupport@theice.com icelinkhelp@theice.com
C28: Simcorp | D28: goldensourceoperations@hoopp.com for now HOOPP To CHECK INTERNALLY
C29: Moody's | D29: goldensourceoperations@hoopp.com for now HOOPP To CHECK INTERNALLY
B30: EST to IST | C30: 9.5

Sheet ADayInLife(ADITLO)
A1: ic | B1: Depends Job # | C1: Job Category | D1: Parent Workflow | E1: Job Chain Name | F1: Sub-Application | G1: Task Name in Job Scheduler | H1: Schema | I1: Node | J1: Task Type | K1: Input or Output File Names | L1: FileName | M1: Time Trigerred (CST/CDT) | N1: Time Trigerred (EST/EDT) | O1: Time Trigerred Until (EST) | P1: Time Trigerred (IST) | Q1: Timeline(EST) | R1: File polling interval | S1: Alerts for Fileload | T1: Frequency | U1: Holiday Calendar Followed | V1: Event/ Script Used | W1: Properties files | X1: Part of Regression Testing | Y1: File Path on the AS or JNM FTP | Z1: Summary of the Job | AA1: UC4 workflow | AB1: Critical Job? | AC1: Avg. Time to Finish | AD1: Business SLO (EST) | AE1: OMNI SLO (EST) | AF1: Max Alert Threshold (mins) | AG1: Configured Alerts | AH1: Alert Send To | AI1: Vendor Details | AJ1: Instructions/Actions | AK1: Escalation Path | AL1: OMNI Readiness Check File Name | AM1: OMNI PIpeline Name to Check | AN1: OMNI Readiness Check File Name Date (considering Effective Date = T) | AO1: Job Chain Run Date (considering Effective Date = T) E.g. T+1 means Monday's data will be loaded on Tuesday | AV1: UC4 SLO (EST)
AO2: Mon | AP2: Tue | AQ2: Wed | AR2: Thu | AS2: Fri | AT2: Sat | AU2: Sun
A3: =MAX(A$1:A1)+1 -> 1 | B3: 31 | C3: Standalone | D3: EQUITY | E3: Standalone | F3: Price Master | G3: HOOPP_BB_Generic_Schedule/HOOPP_BB_GENERIC_Req_FileLoad | H3: GC | J3: BB Request | K3: BB Generic Req | L3: GS.BB.GENERIC.out.20240828 | N3: 0.97916667 | O3: =N3 + TIME(2, 0, 0) -> 1.0625 | P3: =N3+Summary!$C$30/24 -> 1.375 | Q3: T+1 | T3: Daily(Mon-Fri) | AB3: Y | AD3: 0.020833333 | AE3: 0.052083333 | AH3: File Load Alert - GS MS Only (GS to chase Vendor directly) SLO Alert - GS MS, HOOPP | AI3: http://service.bloomberg.com Urgent issues: 1-212-617-4390 Global Technical Support: 1-212-318-2000; DXC Contact: DXC Overnight Tier 1 <dxcovernighttier1@hoopp.com> | AJ3: PLEASE SPECIFY WHAT IS IN THIS FILE SMF OR PRICE FILES?
A4: 2 | B4: 1 | C4: Standalone | D4: EQUITY | E4: Standalone | F4: Price Master | G4: HOOPP_BB_Generic_Resp_Schedule/HOOPP_BB_Trig_GENERIC_FileLoad | H4: GC | J4: FileLoad | K4: BB Generic Response | L4: GS.BB.GENERIC.out.20240828 | N4: 0.98958333 | O4: =N4 + TIME(2, 0, 0) -> 1.0729167 | P4: =N4+Summary!$C$30/24 -> 1.3854167 | Q4: T+1 | R4: Every 1 min | S4: 15 mins | T4: Daily(Mon-Fri) | AB4: Y | AD4: 0.041666667 | AE4: 0.052083333 | AG4: HOOPP_BB_Trig_GENERIC_FileLoad | AH4: File Load Alert - GS MS Only (GS to chase Vendor directly) SLO Alert - GS MS, HOOPP | AI4: http://service.bloomberg.com Urgent issues: 1-212-617-4390 Global Technical Support: 1-212-318-2000; DXC Contact: DXC Overnight Tier 1 <dxcovernighttier1@hoopp.com> | AJ4: PLEASE SPECIFY WHAT IS IN THIS FILE SMF OR PRICE FILES?
A5: 4 | D5: EQUITY | G5: HOOPP_BB_CAX_Req_FileLoad | H5: GC | J5: BB Request | K5: BB Corporate Action Request | L5: GS.BB.CAX.out.20240828 | N5: 0.00069444444 | P5: =N5+(Summary!$C$30)/24 -> 0.39652778 | Q5: T+1 | T5: Daily(Mon-Sun) | AB5: Y | AD5: 0.0625 | AE5: 0.072916667 | AH5: File Load Alert - GS MS Only (GS to chase Vendor directly) SLO Alert - GS MS, HOOPP | AI5: http://service.bloomberg.com Urgent issues: 1-212-617-4390 Global Technical Support: 1-212-318-2000; DXC Contact: DXC Overnight Tier 1 <dxcovernighttier1@hoopp.com> | AJ5: PLEASE SPECIFY WHAT IS IN THIS FILE SMF OR PRICE FILES? | AL5: GS.BB.CAX.out.YYYYMMDD | AM5: GoldenSource Security Reference Pipeline | AN5: T+1 | AO5: T+1 | AP5: T+1 | AQ5: T+1 | AR5: T+1 | AS5: T+1 | AT5: T+1 | AU5: T+1 | AV5: 0.079861111
A6: 3 | B6: 31,2 | C6: Standalone | D6: EQUITY | E6: Standalone | F6: Price Master | G6: HOOPP_BB_ALL_Req_FileLoad | H6: GC | J6: BB Request | K6: BB All Asset Class Request except FX(Currency) | L6: GS.BB.EQFND.out.20240828 GS.BB.CURNCY.out.20240828 GS.BB.NONEQOPT.out.20240828 GS.BB.EQTY.out.20240828 GS.BB.MUNI.out.20240828 GS.BB.EQWRNT.out.20240828 GS.BB.GENTICKERS.out.20240828 GS.BB.EQOPTINDX.out.20240828 GS.BB.CP.out.20240828 GS.BB.PFD.out.20240828 GS.BB.CORPGOV.out.20240828 GS.BB.MTGE.out.20240828 GS.BB.MMKT.out.20240828 | N6: 0.00069444444 | O6: =N6 + TIME(2, 0, 0) -> 0.084027778 | P6: =N6+Summary!$C$30/24 -> 0.39652778 | Q6: T+1 | T6: Daily(Tue-Sat) | AB6: Y | AD6: 0.0625 | AE6: 0.072916667 | AH6: File Load Alert - GS MS Only (GS to chase Vendor directly) SLO Alert - GS MS, HOOPP | AI6: http://service.bloomberg.com Urgent issues: 1-212-617-4390 Global Technical Support: 1-212-318-2000; DXC Contact: DXC Overnight Tier 1 <dxcovernighttier1@hoopp.com> | AJ6: PLEASE SPECIFY WHAT IS IN THIS FILE SMF OR PRICE FILES?
A7: 35.1 | C7: Standalone | D7: MARKIT | E7: Standalone | G7: HOOPP_MOTC_DAILY_SG_FileLoad / HOOPP_MOTC_DAILY_SG_FileLoad_Monday | J7: Fileload | K7: Markit OTC Fileload | L7: HOOPP_SG_DAILY.01Nov24.csv | N7: 0.041666667 | O7: 0.16666667 | Q7: T+1 | R7: Every 10 min | T7: Daily(Mon-Fri) | U7: MARKIT_HOLIDAYPLUS1 | AD7: 0.16666667 | AE7: 0.1875 | AG7: HOOPP_MOTC_DAILY_SG_FileLoad | AI7: Vendor Technical Contact: General support@spglobal.com index_services@spglobal.com Michael.Stone@ihsmarkit.com For any escalation or urgent request: referencedataclientservice@spglobal.com SFTP issues: data.delivery@ihsmarkit.com CALL THIS NUMBER - GOES TO ALL INDIA SUPPORT STAFF: +91 120 611 8051 MK-ValHOOPP@ihsmarkit.com Kamal.Sehgal@ihsmarkit.com Vrinda.Pal@ihsmarkit.com Managers: Sachin.Singhal@ihsmarkit.com Rajesh.Kumar2@ihsmarkit.com Toronto Staff: spencer.wiseman@ihsmarkit.com Abhinit.Kumar@ihsmarkit.com Red red@spglobal.com support@spglobal.com Markit Vol OTCDD@spglobal.com After Hours support: +1 877 762 7548 Corporate Action markitcorporateactions@ihsmarkit.com managedcorporateactions@ihsmarkit.com support@markit.com PE Vals (related to CIFC) MK-PEHOOPP@ihsmarkit.com DL-PE-PEValsSupport@ihsmarkit.com Ashwani.Rai@ihsmarkit.com Vendor Business Contact: Lucas Pettella's Team - 1st point of contact Portfolio Valuation: MK-ValHOOPP@ihsmarkit.com (sydney.workman@spglobal.com, nikita.zinchenko@spglobal.com) CDS Pricing Data: cdssupport@ihsmarkit.com EBS (Formerly known as DeltaOne): DeltaOneSupport@ihsmarkit.com OTC Derivatives Data: OTCDD@spglobal.com CDS Reference Data: red@spglobal.com Iboxx Indices: indices@ihsmarkit.com Cameron Lounsbery (Director - Account Management) Email: Cameron.Lounsbery@spglobal.com Phone: (416)304-6587
A8: 35.2 | C8: Standalone | D8: MARKIT | E8: Standalone | G8: HOOPP_MOTC_DAILY_SG_2_FileLoad / HOOPP_MOTC_DAILY_SG_2_FileLoad_Monday | J8: Fileload | K8: Markit OTC Fileload | L8: HOOPP_SG_DAILY_2.01Nov24.csv | N8: 0.041666667 | O8: 0.16666667 | Q8: T+1 | R8: Every 10 min | T8: Daily(Mon-Fri) | U8: MARKIT_HOLIDAYPLUS1 | AD8: 0.16666667 | AE8: 0.1875 | AG8: HOOPP_MOTC_DAILY_SG_2_FileLoad | AI8: Vendor Technical Contact: General support@spglobal.com index_services@spglobal.com Michael.Stone@ihsmarkit.com For any escalation or urgent request: referencedataclientservice@spglobal.com SFTP issues: data.delivery@ihsmarkit.com CALL THIS NUMBER - GOES TO ALL INDIA SUPPORT STAFF: +91 120 611 8051 MK-ValHOOPP@ihsmarkit.com Kamal.Sehgal@ihsmarkit.com Vrinda.Pal@ihsmarkit.com Managers: Sachin.Singhal@ihsmarkit.com Rajesh.Kumar2@ihsmarkit.com Toronto Staff: spencer.wiseman@ihsmarkit.com Abhinit.Kumar@ihsmarkit.com Red red@spglobal.com support@spglobal.com Markit Vol OTCDD@spglobal.com After Hours support: +1 877 762 7548 Corporate Action markitcorporateactions@ihsmarkit.com managedcorporateactions@ihsmarkit.com support@markit.com PE Vals (related to CIFC) MK-PEHOOPP@ihsmarkit.com DL-PE-PEValsSupport@ihsmarkit.com Ashwani.Rai@ihsmarkit.com Vendor Business Contact: Lucas Pettella's Team - 1st point of contact Portfolio Valuation: MK-ValHOOPP@ihsmarkit.com (sydney.workman@spglobal.com, nikita.zinchenko@spglobal.com) CDS Pricing Data: cdssupport@ihsmarkit.com EBS (Formerly known as DeltaOne): DeltaOneSupport@ihsmarkit.com OTC Derivatives Data: OTCDD@spglobal.com CDS Reference Data: red@spglobal.com Iboxx Indices: indices@ihsmarkit.com Cameron Lounsbery (Director - Account Management) Email: Cameron.Lounsbery@spglobal.com Phone: (416)304-6587
A9: 35.3 | B9: 35.1 | D9: MARKIT | F9: Price Master | G9: HOOPP_PricePublishing_OTC HOOPP_PricePublishing_OTC_DAILY | J9: Markit OTC Price Publishing (Silver+Gold) - Price Derivation - Price Valication - Price Denorm - Price Publishing | K9: Price Publishing | L9: Gold-copy for: MarkitSOI_CDX_TRANCHE MarkitSOI_BESPOKE | N9: 0.041666667 | O9: 0.125 | Q9: T+1 | T9: Daily(Tue-Sat) Daily(Mon-Fri) | U9: MARKIT_HOLIDAYPLUS1 | AD9: 0.16666667 | AE9: 0.1875 | AG9: HOOPP_PricePublishing_OTC_DAILY | AL9: HOOPP_SG_DAILY.DDMonYY.csv | AM9: GoldenSource Market Data Solution Hub Pipeline | AN9: T (on Mo this is Friday) | AO9: T+1 | AP9: T+1 | AQ9: T+1 | AR9: T+1 | AS9: T+3 | AV9: 0.19444444
A10: 35.4 | B10: 35.2 | D10: MARKIT | F10: Price Master | G10: HOOPP_PricePublishing_OTC HOOPP_PricePublishing_OTC_DAILY_2 | J10: Markit OTC Price Publishing (Silver+Gold) - Price Derivation - Price Valication - Price Denorm - Price Publishing | K10: Price Publishing | L10: Gold-copy for: MarkitSOI_ABX MarkitSOI_CDX_OPT | N10: 0.041666667 | O10: 0.125 | Q10: T+1 | T10: Daily(Tue-Sat) Daily(Mon-Fri) | U10: MARKIT_HOLIDAYPLUS1 | AD10: 0.16666667 | AE10: 0.1875 | AG10: HOOPP_PricePublishing_OTC_DAILY_2 | AL10: HOOPP_SG_DAILY_2.DDMonYY.csv | AM10: GoldenSource Market Data Solution Hub Pipeline | AN10: T | AO10: T+1 | AP10: T+1 | AQ10: T+1 | AR10: T+1 | AS10: T+3 | AV10: 0.19444444
A11: 5 | B11: 3 | C11: Standalone | D11: EQUITY | E11: Standalone | F11: Price Master | G11: HOOPP_BB_ALL_Resp_FileLoad | H11: GC | J11: FileLoad | K11: BB All Asset Response | L11: GS.BB.EQFND.out.20240828 GS.BB.CURNCY.out.20240828 GS.BB.NONEQOPT.out.20240828 GS.BB.EQTY.out.20240828 GS.BB.MUNI.out.20240828 GS.BB.EQWRNT.out.20240828 GS.BB.GENTICKERS.out.20240828 GS.BB.EQOPTINDX.out.20240828 GS.BB.CP.out.20240828 GS.BB.PFD.out.20240828 GS.BB.CORPGOV.out.20240828 GS.BB.MTGE.out.20240828 GS.BB.MMKT.out.20240828 | N11: 0.017361111 | O11: =N11 + TIME(2, 0, 0) -> 0.10069444 | P11: =N11+(Summary!$C$30)/24 -> 0.41319444 | Q11: T+1 | R11: Every 1 min | S11: 15 mins | T11: Daily(Tue-Sat) | AB11: Y | AD11: 0.0625 | AE11: 0.072916667 | AG11: HOOPP_BB_ALL_Resp_FileLoad | AH11: File Load Alert - GS MS Only (GS to chase Vendor directly) SLO Alert - GS MS, HOOPP | AI11: http://service.bloomberg.com Urgent issues: 1-212-617-4390 Global Technical Support: 1-212-318-2000; DXC Contact: DXC Overnight Tier 1 <dxcovernighttier1@hoopp.com> | AJ11: PLEASE SPECIFY WHAT IS IN THIS FILE SMF OR PRICE FILES? | AL11: GS.BB.EQTY.out.YYYYMMDD | AM11: GoldenSource Security Reference Pipeline | AN11: T+1 | AO11: T+1 | AP11: T+1 | AQ11: T+1 | AR11: T+1 | AS11: T+1 | AV11: 0.079861111
A12: 6 | B12: 4 | C12: Standalone | D12: EQUITY | E12: Standalone | G12: HOOPP_BB_Trig_CAX_FileLoad | H12: GC | J12: FileLoad | K12: BB Corporate Action Response | L12: GS.BB.CAX.out.20240828 | N12: 0.027777778 | O12: =N12 + TIME(2, 0, 0) -> 0.11111111 | P12: =N12+(Summary!$C$30)/24 -> 0.42361111 | Q12: T+1 | R12: Every 1 min | S12: 15 mins | T12: Daily(Mon-Sun) | AD12: 0.125 | AE12: 0.072916667 | AG12: HOOPP_BB_Trig_CAX_FileLoad | AH12: File Load Alert - GS MS Only (GS to chase Vendor directly) SLO Alert - GS MS, HOOPP | AI12: http://service.bloomberg.com Urgent issues: 1-212-617-4390 Global Technical Support: 1-212-318-2000; DXC Contact: DXC Overnight Tier 1 <dxcovernighttier1@hoopp.com> | AL12: GS.BB.CAX.out.YYYYMMDD | AM12: GoldenSource Security Reference Pipeline | AN12: T+1 | AO12: T+1 | AP12: T+1 | AQ12: T+1 | AR12: T+1 | AS12: T+1 | AT12: T+1 | AU12: T+1 | AV12: 0.079861111
A13: 8 | C13: Standalone | E13: Standalone | G13: HOOPP_Markit_REDEntity_FileLoad | H13: GC | J13: FileLoad | K13: Markit RED Obligation | L13: V10%20Red%20Obligation1724826602201.xml V11%20Red%20Obligation1724826602201.xml | N13: 0.10416667 | O13: =N13 + TIME(2, 0, 0) -> 0.1875 | P13: =N13+(Summary!$C$30)/24 -> 0.5 | Q13: T+1 | R13: Every 5 mins | S13: 16 mins | T13: Daily(Mon-Fri) Daily(Tue-Sat) | AD13: 0.14583333 | AE13: 0.15625 | AG13: HOOPP_Markit_REDEntity_FileLoad | AH13: File Load Alert - GS MS Only (GS to chase Vendor directly) SLO Alert - GS MS, HOOPP | AI13: Vendor Technical Contact: General support@spglobal.com index_services@spglobal.com Michael.Stone@ihsmarkit.com For any escalation or urgent request: referencedataclientservice@spglobal.com SFTP issues: data.delivery@ihsmarkit.com CALL THIS NUMBER - GOES TO ALL INDIA SUPPORT STAFF: +91 120 611 8051 MK-ValHOOPP@ihsmarkit.com Kamal.Sehgal@ihsmarkit.com Vrinda.Pal@ihsmarkit.com Managers: Sachin.Singhal@ihsmarkit.com Rajesh.Kumar2@ihsmarkit.com Toronto Staff: spencer.wiseman@ihsmarkit.com Abhinit.Kumar@ihsmarkit.com Red red@spglobal.com support@spglobal.com Markit Vol OTCDD@spglobal.com After Hours support: +1 877 762 7548 Corporate Action markitcorporateactions@ihsmarkit.com managedcorporateactions@ihsmarkit.com support@markit.com PE Vals (related to CIFC) MK-PEHOOPP@ihsmarkit.com DL-PE-PEValsSupport@ihsmarkit.com Ashwani.Rai@ihsmarkit.com Vendor Business Contact: Lucas Pettella's Team - 1st point of contact Portfolio Valuation: MK-ValHOOPP@ihsmarkit.com (sydney.workman@spglobal.com, nikita.zinchenko@spglobal.com) CDS Pricing Data: cdssupport@ihsmarkit.com EBS (Formerly known as DeltaOne): DeltaOneSupport@ihsmarkit.com OTC Derivatives Data: OTCDD@spglobal.com CDS Reference Data: red@spglobal.com Iboxx Indices: indices@ihsmarkit.com Cameron Lounsbery (Director - Account Management) Email: Cameron.Lounsbery@spglobal.com Phone: (416)304-6587 | AL13: V11_Red_Obligation_YYYYMMDD.xml | AM13: GoldenSource Security Reference Pipeline | AN13: T+1 | AO13: T+1 | AP13: T+1 | AQ13: T+1 | AR13: T+1 | AS13: T+1 | AV13: 0.16319444
A14: 9 | C14: Standalone | E14: Standalone | G14: HOOPP_Markit_REDEntity_FileLoad | H14: GC | J14: FileLoad | K14: Markit RED Entity | L14: V11%20Red%20Entity1724826870563.xml V12_Red_Entity_20250219.xml | N14: 0.10416667 | O14: =N14 + TIME(2, 0, 0) -> 0.1875 | P14: =N14+(Summary!$C$30)/24 -> 0.5 | Q14: T+1 | R14: Every 5 mins | S14: 16 mins | T14: Daily(Mon-Fri) Daily(Tue-Sat) | AD14: 0.14583333 | AE14: 0.15625 | AG14: HOOPP_Markit_REDEntity_FileLoad | AH14: File Load Alert - GS MS Only (GS to chase Vendor directly) SLO Alert - GS MS, HOOPP | AI14: Vendor Technical Contact: General support@spglobal.com index_services@spglobal.com Michael.Stone@ihsmarkit.com For any escalation or urgent request: referencedataclientservice@spglobal.com SFTP issues: data.delivery@ihsmarkit.com CALL THIS NUMBER - GOES TO ALL INDIA SUPPORT STAFF: +91 120 611 8051 MK-ValHOOPP@ihsmarkit.com Kamal.Sehgal@ihsmarkit.com Vrinda.Pal@ihsmarkit.com Managers: Sachin.Singhal@ihsmarkit.com Rajesh.Kumar2@ihsmarkit.com Toronto Staff: spencer.wiseman@ihsmarkit.com Abhinit.Kumar@ihsmarkit.com Red red@spglobal.com support@spglobal.com Markit Vol OTCDD@spglobal.com After Hours support: +1 877 762 7548 Corporate Action markitcorporateactions@ihsmarkit.com managedcorporateactions@ihsmarkit.com support@markit.com PE Vals (related to CIFC) MK-PEHOOPP@ihsmarkit.com DL-PE-PEValsSupport@ihsmarkit.com Ashwani.Rai@ihsmarkit.com Vendor Business Contact: Lucas Pettella's Team - 1st point of contact Portfolio Valuation: MK-ValHOOPP@ihsmarkit.com (sydney.workman@spglobal.com, nikita.zinchenko@spglobal.com) CDS Pricing Data: cdssupport@ihsmarkit.com EBS (Formerly known as DeltaOne): DeltaOneSupport@ihsmarkit.com OTC Derivatives Data: OTCDD@spglobal.com CDS Reference Data: red@spglobal.com Iboxx Indices: indices@ihsmarkit.com Cameron Lounsbery (Director - Account Management) Email: Cameron.Lounsbery@spglobal.com Phone: (416)304-6587 | AL14: V12_Red_Entity_YYYYMMDD.xml | AM14: GoldenSource Security Reference Pipeline | AN14: T+1 | AO14: T+1 | AP14: T+1 | AQ14: T+1 | AR14: T+1 | AS14: T+1 | AV14: 0.16319444
A15: 10 | C15: Standalone | D15: MARKIT | E15: Standalone | F15: Price Master | G15: HOOPP_CreditIndexPricing_FileLoad | H15: GC | J15: FileLoad | K15: Markit Credit Index Price (T-1) | L15: New_Credit_Index_Pricing_20240827.zip New_Credit_Index_Pricing_20240827.zip New_Credit_Index_Pricing_20240827.zip | N15: 0.0625 | O15: =N15 + TIME(2, 0, 0) -> 0.14583333 | P15: =N15+(Summary!$C$30)/24 -> 0.45833333 | Q15: T+1 | R15: Every 5 mins | S15: 16 mins | T15: Daily(Tue-Sat) | AD15: 0.14583333 | AE15: 0.15625 | AG15: HOOPP_CreditIndexPricing_FileLoad | AH15: File Load Alert - GS MS Only (GS to chase Vendor directly) SLO Alert - GS MS, HOOPP | AI15: Vendor Technical Contact: General support@spglobal.com index_services@spglobal.com Michael.Stone@ihsmarkit.com For any escalation or urgent request: referencedataclientservice@spglobal.com SFTP issues: data.delivery@ihsmarkit.com CALL THIS NUMBER - GOES TO ALL INDIA SUPPORT STAFF: +91 120 611 8051 MK-ValHOOPP@ihsmarkit.com Kamal.Sehgal@ihsmarkit.com Vrinda.Pal@ihsmarkit.com Managers: Sachin.Singhal@ihsmarkit.com Rajesh.Kumar2@ihsmarkit.com Toronto Staff: spencer.wiseman@ihsmarkit.com Abhinit.Kumar@ihsmarkit.com Red red@spglobal.com support@spglobal.com Markit Vol OTCDD@spglobal.com After Hours support: +1 877 762 7548 Corporate Action markitcorporateactions@ihsmarkit.com managedcorporateactions@ihsmarkit.com support@markit.com PE Vals (related to CIFC) MK-PEHOOPP@ihsmarkit.com DL-PE-PEValsSupport@ihsmarkit.com Ashwani.Rai@ihsmarkit.com Vendor Business Contact: Lucas Pettella's Team - 1st point of contact Portfolio Valuation: MK-ValHOOPP@ihsmarkit.com (sydney.workman@spglobal.com, nikita.zinchenko@spglobal.com) CDS Pricing Data: cdssupport@ihsmarkit.com EBS (Formerly known as DeltaOne): DeltaOneSupport@ihsmarkit.com OTC Derivatives Data: OTCDD@spglobal.com CDS Reference Data: red@spglobal.com Iboxx Indices: indices@ihsmarkit.com Cameron Lounsbery (Director - Account Management) Email: Cameron.Lounsbery@spglobal.com Phone: (416)304-6587 | AJ15: Update to reflect 3 file loads | AV15: 0.15625
A16: 10.1 | B16: 10 | D16: MARKIT | F16: Price Master | G16: HOOPP_PricePublishing_MarkitSOI_CDX_CDS | J16: Markit OTC Price Publishing (Silver+Gold) - Price Derivation - Price Valication - Price Denorm - Price Publishing | K16: Price Publishing | L16: Silver & gold for MarkitSOI_CDX_CDS Silver prices & key figures for all Markit Credit Index securities | N16: 0.0625 | O16: 0.1875 | Q16: T+1 | T16: Daily(Tue-Sat) | AD16: 0.14583333 | AE16: 0.15625 | AG16: HOOPP_PricePublishing_MarkitSOI_CDX_CDS | AL16: New_Credit_Index_Pricing_YYYYMMDD.zip | AM16: GoldenSource Market Data Solution Hub Pipeline | AN16: T | AO16: T+1 | AP16: T+1 | AQ16: T+1 | AR16: T+1 | AS16: T+1 | AV16: 0.16319444
A17: 10.2 | B17: 36, 10 | D17: MARKIT | F17: Price Master | G17: HOOPP_PricePublishing_MarkitSOI_CDX_CDS | J17: Markit OTC Price Publishing (Silver+Gold) - Price Derivation - Price Valication - Price Denorm - Price Publishing | K17: Price Publishing | L17: Silver & gold for MarkitSOI_CC_CDX_CDS | N17: 0.0625 | O17: 0.1875 | Q17: T+1 | T17: Daily(Tue-Sat) | AD17: 0.14583333 | AE17: 0.15625 | AG17: HOOPP_PricePublishing_MarkitSOI_CDX_CDS | AL17: New_Credit_Index_Pricing_YYYYMMDD.zip | AM17: GoldenSource Market Data Solution Hub Pipeline | AN17: T | AO17: T+1 | AP17: T+1 | AQ17: T+1 | AR17: T+1 | AS17: T+1 | AV17: 0.16319444
A18: 11 | C18: Standalone | D18: MARKIT | E18: Standalone | F18: Price Master | G18: HOOPP_CreditIndexPricing_FileLoad HOOPP_CDSBasicPricing_FileLoad | H18: GC | J18: FileLoad | K18: Markit Composite CDS Basic Pricing(T-1) | L18: Composite_CDS_Basic_Pricing_20240827.zip | N18: 0.0625 | O18: =N18 + TIME(2, 0, 0) -> 0.14583333 | P18: =N18+(Summary!$C$30)/24 -> 0.45833333 | Q18: T+1 | R18: Every 5 mins | S18: 16 mins | T18: Daily(Tue-Sat) | AD18: 0.125 | AE18: 0.14583333 | AG18: HOOPP_CDSBasicPricing_FileLoad | AH18: File Load Alert - GS MS Only (GS to chase Vendor directly) SLO Alert - GS MS, HOOPP | AI18: Vendor Technical Contact: General support@spglobal.com index_services@spglobal.com Michael.Stone@ihsmarkit.com For any escalation or urgent request: referencedataclientservice@spglobal.com SFTP issues: data.delivery@ihsmarkit.com CALL THIS NUMBER - GOES TO ALL INDIA SUPPORT STAFF: +91 120 611 8051 MK-ValHOOPP@ihsmarkit.com Kamal.Sehgal@ihsmarkit.com Vrinda.Pal@ihsmarkit.com Managers: Sachin.Singhal@ihsmarkit.com Rajesh.Kumar2@ihsmarkit.com Toronto Staff: spencer.wiseman@ihsmarkit.com Abhinit.Kumar@ihsmarkit.com Red red@spglobal.com support@spglobal.com Markit Vol OTCDD@spglobal.com After Hours support: +1 877 762 7548 Corporate Action markitcorporateactions@ihsmarkit.com managedcorporateactions@ihsmarkit.com support@markit.com PE Vals (related to CIFC) MK-PEHOOPP@ihsmarkit.com DL-PE-PEValsSupport@ihsmarkit.com Ashwani.Rai@ihsmarkit.com Vendor Business Contact: Lucas Pettella's Team - 1st point of contact Portfolio Valuation: MK-ValHOOPP@ihsmarkit.com (sydney.workman@spglobal.com, nikita.zinchenko@spglobal.com) CDS Pricing Data: cdssupport@ihsmarkit.com EBS (Formerly known as DeltaOne): DeltaOneSupport@ihsmarkit.com OTC Derivatives Data: OTCDD@spglobal.com CDS Reference Data: red@spglobal.com Iboxx Indices: indices@ihsmarkit.com Cameron Lounsbery (Director - Account Management) Email: Cameron.Lounsbery@spglobal.com Phone: (416)304-6587 | AV18: 0.14583333
A19: 11.1 | B19: 11 | D19: MARKIT | F19: Price Master | J19: Markit Composite CDS Price Publishing (Silver) - Price Denorm - Price Publishing | K19: Price Publishing | L19: Silver prices & key figures for all Markit Spread securities | N19: 0.10416667 | O19: 0.1875 | Q19: T+1 | T19: Daily(Tue-Sat) | AD19: 0.125 | AE19: 0.14583333 | AG19: HOOPP_PricePublishing_Markit_Schedule | AV19: 0.14583333
A20: 12 | C20: Standalone | E20: Standalone | G20: HOOPP_BB_CreditRisk_FileLoad | H20: GC | J20: FileLoad | K20: BB Corporate Structure(T-1) | L20: creditRiskV3.dif.gz | N20: 0.78125 | O20: =N20 + TIME(2, 0, 0) -> 0.86458333 | P20: =N20+(Summary!$C$30)/24 -> 1.1770833 | Q20: T+1 | R20: Every 10 mins | S20: 21 mins | T20: Daily(Mon-Sun) | Z20: Issuer data, No SOI | AD20: 0.8125 | AE20: 0.82291667 | AG20: HOOPP_BB_CreditRisk_FileLoad | AH20: File Load Alert - GS MS Only (GS to chase Vendor directly) SLO Alert - GS MS, HOOPP | AI20: http://service.bloomberg.com Urgent issues: 1-212-617-4390 Global Technical Support: 1-212-318-2000 | AL20: creditRiskV3.dif.gz | AM20: GoldenSource Security Reference Pipeline | AN20: NA (Date not available in the filename) | AO20: T | AP20: T | AQ20: T | AR20: T | AS20: T | AT20: T | AU20: T | AV20: 0.82986111
A21: 13 | C21: Standalone | E21: Standalone | G21: HOOPP_Moodys_FileLoad | H21: GC | J21: FileLoad | K21: Moody's RDS Instrument Ratings(24Hour delta) | L21: cfg_inst_current_rating_00_Utf8_24Hour_Delta_000028_20240828_000000_part01_0110final.split cfg_inst_current_rating_00_Utf8_24Hour_Delta_000028_20240828_000000_part01_0111final.split cfg_inst_current_rating_00_Utf8_24Hour_Delta_000028_20240828_000000_part01_0115final.split cfg_inst_current_rating_00_Utf8_24Hour_Delta_000028_20240828_000000_part01_011final.split cfg_inst_current_rating_00_Utf8_24Hour_Delta_000028_20240828_000000_part01_012final.split cfg_inst_current_rating_00_Utf8_24Hour_Delta_000028_20240828_000000_part01_013final.split cfg_inst_current_rating_00_Utf8_24Hour_Delta_000028_20240828_000000_part01_014final.split cfg_inst_current_rating_00_Utf8_24Hour_Delta_000028_20240828_000000_part01_015final.split cfg_inst_current_rating_00_Utf8_24Hour_Delta_000028_20240828_000000_part01_016final.split cfg_inst_current_rating_00_Utf8_24Hour_Delta_000028_20240828_000000_part01_017final.split cfg_inst_current_rating_00_Utf8_24Hour_Delta_000028_20240828_000000_part01_018final.split | N21: 0.875 | O21: =N21 + TIME(2, 0, 0) -> 0.95833333 | P21: =N21+([1]Summary!$C$30)/24 -> 0.875 | Q21: T | R21: Every 10 mins | S21: 21 mins | T21: Daily(Mon-Sat) Daily(Sun-Fri) | AD21: 0.91666667 | AE21: 0.92708333 | AG21: HOOPP_Moodys_FileLoad | AH21: File Load Alert - GS MS Only (GS to chase Vendor directly) SLO Alert - GS MS, HOOPP | AI21: Maura Bermiss: Maura.Bermiss@moodys.com | AL21: cfg_inst_current_rating_00_Utf8_24Hour_Delta_0000DD_YYYYMMDD_000000_part01*.split | AM21: GoldenSource Security Reference Pipeline | AN21: T+1 | AO21: T | AP21: T | AQ21: T | AR21: T | AS21: T | AU21: T | AV21: 0.93402778
A22: 14 | C22: Standalone | E22: Standalone | G22: HOOPP_Moodys_FileLoad | H22: GC | J22: FileLoad | K22: Moody's RDS Organization Ratings (24Hour delta) | L22: cfg_organization_current_rating_00_Utf8_24Hour_Delta_000028_20240828_000000_part01_010.split cfg_organization_current_rating_00_Utf8_24Hour_Delta_000028_20240828_000000_part01_011.split cfg_organization_current_rating_00_Utf8_24Hour_Delta_000028_20240828_000000_part01_012.split cfg_organization_current_rating_00_Utf8_24Hour_Delta_000028_20240828_000000_part01_013.split cfg_organization_current_rating_00_Utf8_24Hour_Delta_000028_20240828_000000_part01_014.split cfg_organization_current_rating_00_Utf8_24Hour_Delta_000028_20240828_000000_part01_015.split cfg_organization_current_rating_00_Utf8_24Hour_Delta_000028_20240828_000000_part01_016.split | N22: 0.875 | O22: =N22 + TIME(2, 0, 0) -> 0.95833333 | P22: =N22+([1]Summary!$C$30)/24 -> 0.875 | Q22: T | R22: Every 10 mins | S22: 21 mins | T22: Daily(Mon-Sat) Daily(Sun-Fri) | AD22: 0.91666667 | AE22: 0.92708333 | AG22: HOOPP_Moodys_FileLoad | AH22: File Load Alert - GS MS Only (GS to chase Vendor directly) SLO Alert - GS MS, HOOPP | AI22: Maura Bermiss: Maura.Bermiss@moodys.com | AL22: cfg_organization_current_rating_00_Utf8_24Hour_Delta_0000DD_YYYYMMDD_000000_part01*.split | AM22: GoldenSource Security Reference Pipeline | AN22: T+1 | AO22: T | AP22: T | AQ22: T | AR22: T | AS22: T | AU22: T | AV22: 0.93402778
A23: 7 | B23: 5 | D23: EQUITY | F23: Price Master | H23: GC | J23: BB Silver + Equities Gold Prices - Price Derivation - Price Valication - Price Denorm - Price Publishing | K23: Price Publishing | N23: 0.052083333 | P23: =N23+(Summary!$C$30)/24 -> 0.44791667 | Q23: T+1 | T23: Daily(Tue-Sat) | AD23: 0.083333333 | AE23: 0.09375 | AG23: HOOPP_PricePublishing_Equity_Schedule | AL23: GS.BB.EQTY.out.YYYYMMDD | AM23: GoldenSource Market Data Solution Hub Pipeline | AN23: T+1 | AO23: T+1 | AP23: T+1 | AQ23: T+1 | AR23: T+1 | AS23: T+1 | AV23: 0.10069444
A24: 33 | C24: Standalone | E24: Standalone | G24: HOOPP_Moodys_FullFile_FileLoad | H24: GC | J24: FileLoad | K24: Moody's RDS Instrument Ratings(baseline) | L24: cfg_inst_current_rating_Utf8_Baseline_Daily_20241027_000000_part09_0995final.split cfg_inst_current_rating_Utf8_Baseline_Daily_20241027_000000_part09_0999final.split cfg_inst_current_rating_Utf8_Baseline_Daily_20241027_000000_part09_0998final.split cfg_inst_current_rating_Utf8_Baseline_Daily_20241027_000000_part09_0988final.split cfg_inst_current_rating_Utf8_Baseline_Daily_20241027_000000_part09_0992final.split | N24: 0.875 | O24: =N24 + TIME(2, 0, 0) -> 0.95833333 | P24: =N24+([1]Summary!$C$30)/24 -> 0.875 | Q24: T | R24: Every 10 mins | S24: 30 mins | T24: Sat | AD24: 0.91666667 | AE24: 0.92708333 | AH24: File Load Alert - GS MS Only (GS to chase Vendor directly) SLO Alert - GS MS, HOOPP | AI24: Maura Bermiss: Maura.Bermiss@moodys.com | AL24: cfg_inst_current_rating_Utf8_Baseline_Daily_YYYYMMDD_000000_part01*.split | AM24: GoldenSource Security Reference Pipeline | AN24: T+1 | AT24: T | AV24: 0.93402778
A25: 34 | C25: Standalone | E25: Standalone | G25: HOOPP_Moodys_FullFile_FileLoad | H25: GC | J25: FileLoad | K25: Moody's RDS Organization Ratings (baseline) | L25: cfg_organization_current_rating_Utf8_Baseline_Daily_20241027_000000_part03_0499.split cfg_organization_current_rating_Utf8_Baseline_Daily_20241027_000000_part03_0498.split cfg_organization_current_rating_Utf8_Baseline_Daily_20241027_000000_part03_0497.split cfg_organization_current_rating_Utf8_Baseline_Daily_20241027_000000_part03_0495.split | N25: 0.875 | O25: =N25 + TIME(2, 0, 0) -> 0.95833333 | P25: =N25+([1]Summary!$C$30)/24 -> 0.875 | Q25: T | R25: Every 10 mins | S25: 30 mins | T25: Sat | AD25: 0.91666667 | AE25: 0.92708333 | AH25: File Load Alert - GS MS Only (GS to chase Vendor directly) SLO Alert - GS MS, HOOPP | AI25: Maura Bermiss: Maura.Bermiss@moodys.com | AL25: cfg_organization_current_rating_Utf8_Baseline_Daily_YYYYMMDD_000000_part01*.split | AM25: GoldenSource Security Reference Pipeline | AN25: T+1 | AT25: T | AV25: 0.93402778
A26: 15 | C26: Standalone | E26: Standalone | G26: HOOPP_SCD_4AM_FileLoad | H26: GC | J26: FileLoad | K26: Simcorp | L26: SCD_SMF_280824040122.csv | N26: 0.16666667 | O26: =N26 + TIME(2, 0, 0) -> 0.25 | P26: =N26+(Summary!$C$30)/24 -> 0.5625 | Q26: T+1 | R26: Every 3 mins | S26: 10 mins | T26: Daily(Mon-Sat) | AB26: y | AD26: 0.1875 | AE26: 0.20833333 | AG26: HOOPP_SCD_4AM_FileLoad | AH26: File Load Alert - GS MS Only (GS to chase Vendor directly) SLO Alert - GS MS, HOOPP | AI26: DXC Overnight Tier 1 <dxcovernighttier1@hoopp.com>; Golden Source Operations <goldensourceoperations@hoopp.com>; ISG-DTS-Operations <isg-dts-operations@hoopp.com> | AV26: 0.20833333
A27: 16 | G27: HOOPP_Markit_REDINDICES_CDX_FileLoad | H27: GC | J27: FileLoad | K27: Markit RED Credit Indices CDX | L27: V10%20Red%20Indices1724832057006.xml V11_CDX_Red_Indices_20250129.xml V11_CDX_Red_Indices_20250129.xml.inxdup V11_CDX_Red_Indices_20250129.xml.dedup | N27: 0.16666667 | O27: =N27 + TIME(2, 0, 0) -> 0.25 | P27: =N27+(Summary!$C$30)/24 -> 0.5625 | Q27: T+1 | R27: Every 5 mins | S27: 16 mins | T27: Daily(Mon-Fri) Daily(Tue-Sat) | AD27: 0.1875 | AE27: 0.21875 | AG27: HOOPP_Markit_REDINDICES_CDX_FileLoad | AH27: File Load Alert - GS MS Only (GS to chase Vendor directly) SLO Alert - GS MS, HOOPP | AI27: Vendor Technical Contact: General support@spglobal.com index_services@spglobal.com Michael.Stone@ihsmarkit.com For any escalation or urgent request: referencedataclientservice@spglobal.com SFTP issues: data.delivery@ihsmarkit.com CALL THIS NUMBER - GOES TO ALL INDIA SUPPORT STAFF: +91 120 611 8051 MK-ValHOOPP@ihsmarkit.com Kamal.Sehgal@ihsmarkit.com Vrinda.Pal@ihsmarkit.com Managers: Sachin.Singhal@ihsmarkit.com Rajesh.Kumar2@ihsmarkit.com Toronto Staff: spencer.wiseman@ihsmarkit.com Abhinit.Kumar@ihsmarkit.com Red red@spglobal.com support@spglobal.com Markit Vol OTCDD@spglobal.com After Hours support: +1 877 762 7548 Corporate Action markitcorporateactions@ihsmarkit.com managedcorporateactions@ihsmarkit.com support@markit.com PE Vals (related to CIFC) MK-PEHOOPP@ihsmarkit.com DL-PE-PEValsSupport@ihsmarkit.com Ashwani.Rai@ihsmarkit.com Vendor Business Contact: Lucas Pettella's Team - 1st point of contact Portfolio Valuation: MK-ValHOOPP@ihsmarkit.com (sydney.workman@spglobal.com, nikita.zinchenko@spglobal.com) CDS Pricing Data: cdssupport@ihsmarkit.com EBS (Formerly known as DeltaOne): DeltaOneSupport@ihsmarkit.com OTC Derivatives Data: OTCDD@spglobal.com CDS Reference Data: red@spglobal.com Iboxx Indices: indices@ihsmarkit.com Cameron Lounsbery (Director - Account Management) Email: Cameron.Lounsbery@spglobal.com Phone: (416)304-6587 | AL27: V11_CDX_Red_Indices_YYYYMMDD.xml | AM27: GoldenSource Security Reference Pipeline | AN27: T+1 | AO27: T+1 | AP27: T+1 | AQ27: T+1 | AR27: T+1 | AS27: T+1 | AV27: 0.22569444
A28: 17 | G28: HOOPP_Markit_REDINDICES_CDX_FileLoad | H28: GC | J28: FileLoad | K28: Markit RED Credit Indices EURO | L28: V10%20Red%20Indices%20Dynamic1724832001075.xml V11_ITRAXX-EUROPE_Red_Indices_20250129.xml V11_ITRAXX-EUROPE_Red_Indices_20250129.xml.inxdup V11_ITRAXX-EUROPE_Red_Indices_20250129.xml.dedup | N28: 0.16666667 | O28: =N28 + TIME(2, 0, 0) -> 0.25 | P28: =N28+(Summary!$C$30)/24 -> 0.5625 | Q28: T+1 | R28: Every 5 mins | S28: 16 mins | T28: Daily(Mon-Fri) Daily(Tue-Sat) | AD28: 0.1875 | AE28: 0.21875 | AG28: HOOPP_Markit_REDINDICES_CDX_FileLoad | AH28: File Load Alert - GS MS Only (GS to chase Vendor directly) SLO Alert - GS MS, HOOPP | AI28: Vendor Technical Contact: General support@spglobal.com index_services@spglobal.com Michael.Stone@ihsmarkit.com For any escalation or urgent request: referencedataclientservice@spglobal.com SFTP issues: data.delivery@ihsmarkit.com CALL THIS NUMBER - GOES TO ALL INDIA SUPPORT STAFF: +91 120 611 8051 MK-ValHOOPP@ihsmarkit.com Kamal.Sehgal@ihsmarkit.com Vrinda.Pal@ihsmarkit.com Managers: Sachin.Singhal@ihsmarkit.com Rajesh.Kumar2@ihsmarkit.com Toronto Staff: spencer.wiseman@ihsmarkit.com Abhinit.Kumar@ihsmarkit.com Red red@spglobal.com support@spglobal.com Markit Vol OTCDD@spglobal.com After Hours support: +1 877 762 7548 Corporate Action markitcorporateactions@ihsmarkit.com managedcorporateactions@ihsmarkit.com support@markit.com PE Vals (related to CIFC) MK-PEHOOPP@ihsmarkit.com DL-PE-PEValsSupport@ihsmarkit.com Ashwani.Rai@ihsmarkit.com Vendor Business Contact: Lucas Pettella's Team - 1st point of contact Portfolio Valuation: MK-ValHOOPP@ihsmarkit.com (sydney.workman@spglobal.com, nikita.zinchenko@spglobal.com) CDS Pricing Data: cdssupport@ihsmarkit.com EBS (Formerly known as DeltaOne): DeltaOneSupport@ihsmarkit.com OTC Derivatives Data: OTCDD@spglobal.com CDS Reference Data: red@spglobal.com Iboxx Indices: indices@ihsmarkit.com Cameron Lounsbery (Director - Account Management) Email: Cameron.Lounsbery@spglobal.com Phone: (416)304-6587 | AL28: V11_ITRAXX-EUROPE_Red_Indices_YYYYMMDD.xml | AM28: GoldenSource Security Reference Pipeline | AN28: T+1 | AO28: T+1 | AP28: T+1 | AQ28: T+1 | AR28: T+1 | AS28: T+1 | AV28: 0.22569444
A29: 18 | G29: HOOPP_Markit_REDINDICES_CDX_FileLoad | H29: GC | J29: FileLoad | K29: Markit RED Credit Indices ASIA | L29: V10%20Red%20Indices%20Dynamic1724832091625.xml V11_ITRAXX-ASIA_Red_Indices_20250129.xml V11_ITRAXX-ASIA_Red_Indices_20250129.xml.inxdup V11_ITRAXX-ASIA_Red_Indices_20250129.xml.dedup | N29: 0.16666667 | O29: =N29 + TIME(2, 0, 0) -> 0.25 | P29: =N29+(Summary!$C$30)/24 -> 0.5625 | Q29: T+1 | R29: Every 5 mins | S29: 16 mins | T29: Daily(Mon-Fri) Daily(Tue-Sat) | AD29: 0.1875 | AE29: 0.21875 | AG29: HOOPP_Markit_REDINDICES_CDX_FileLoad | AH29: File Load Alert - GS MS Only (GS to chase Vendor directly) SLO Alert - GS MS, HOOPP | AI29: Vendor Technical Contact: General support@spglobal.com index_services@spglobal.com Michael.Stone@ihsmarkit.com For any escalation or urgent request: referencedataclientservice@spglobal.com SFTP issues: data.delivery@ihsmarkit.com CALL THIS NUMBER - GOES TO ALL INDIA SUPPORT STAFF: +91 120 611 8051 MK-ValHOOPP@ihsmarkit.com Kamal.Sehgal@ihsmarkit.com Vrinda.Pal@ihsmarkit.com Managers: Sachin.Singhal@ihsmarkit.com Rajesh.Kumar2@ihsmarkit.com Toronto Staff: spencer.wiseman@ihsmarkit.com Abhinit.Kumar@ihsmarkit.com Red red@spglobal.com support@spglobal.com Markit Vol OTCDD@spglobal.com After Hours support: +1 877 762 7548 Corporate Action markitcorporateactions@ihsmarkit.com managedcorporateactions@ihsmarkit.com support@markit.com PE Vals (related to CIFC) MK-PEHOOPP@ihsmarkit.com DL-PE-PEValsSupport@ihsmarkit.com Ashwani.Rai@ihsmarkit.com Vendor Business Contact: Lucas Pettella's Team - 1st point of contact Portfolio Valuation: MK-ValHOOPP@ihsmarkit.com (sydney.workman@spglobal.com, nikita.zinchenko@spglobal.com) CDS Pricing Data: cdssupport@ihsmarkit.com EBS (Formerly known as DeltaOne): DeltaOneSupport@ihsmarkit.com OTC Derivatives Data: OTCDD@spglobal.com CDS Reference Data: red@spglobal.com Iboxx Indices: indices@ihsmarkit.com Cameron Lounsbery (Director - Account Management) Email: Cameron.Lounsbery@spglobal.com Phone: (416)304-6587 | AL29: V11_ITRAXX-ASIA_Red_Indices_YYYYMMDD.xml | AM29: GoldenSource Security Reference Pipeline | AN29: T+1 | AO29: T+1 | AP29: T+1 | AQ29: T+1 | AR29: T+1 | AS29: T+1 | AV29: 0.22569444
A30: 18 | G30: HOOPP_Markit_REDINDICES_CDX_FileLoad | H30: GC | J30: FileLoad | K30: Markit RED Credit Indices SOVX | L30: V10%20Red%20Indices%20Dynamic1724832091625.xml V11_ITRAXX-SOVX_Red_Indices_20250129.xml.dedup V11_ITRAXX-SOVX_Red_Indices_20250129.xml.inxdup V11_ITRAXX-SOVX_Red_Indices_20250129.xml | N30: 0.16666667 | O30: =N30 + TIME(2, 0, 0) -> 0.25 | P30: =N30+(Summary!$C$30)/24 -> 0.5625 | Q30: T+1 | R30: Every 5 mins | S30: 16 mins | T30: Daily(Mon-Fri) Daily(Tue-Sat) | AD30: 0.1875 | AE30: 0.21875 | AG30: HOOPP_Markit_REDINDICES_CDX_FileLoad | AH30: File Load Alert - GS MS Only (GS to chase Vendor directly) SLO Alert - GS MS, HOOPP | AI30: Vendor Technical Contact: General support@spglobal.com index_services@spglobal.com Michael.Stone@ihsmarkit.com For any escalation or urgent request: referencedataclientservice@spglobal.com SFTP issues: data.delivery@ihsmarkit.com CALL THIS NUMBER - GOES TO ALL INDIA SUPPORT STAFF: +91 120 611 8051 MK-ValHOOPP@ihsmarkit.com Kamal.Sehgal@ihsmarkit.com Vrinda.Pal@ihsmarkit.com Managers: Sachin.Singhal@ihsmarkit.com Rajesh.Kumar2@ihsmarkit.com Toronto Staff: spencer.wiseman@ihsmarkit.com Abhinit.Kumar@ihsmarkit.com Red red@spglobal.com support@spglobal.com Markit Vol OTCDD@spglobal.com After Hours support: +1 877 762 7548 Corporate Action markitcorporateactions@ihsmarkit.com managedcorporateactions@ihsmarkit.com support@markit.com PE Vals (related to CIFC) MK-PEHOOPP@ihsmarkit.com DL-PE-PEValsSupport@ihsmarkit.com Ashwani.Rai@ihsmarkit.com Vendor Business Contact: Lucas Pettella's Team - 1st point of contact Portfolio Valuation: MK-ValHOOPP@ihsmarkit.com (sydney.workman@spglobal.com, nikita.zinchenko@spglobal.com) CDS Pricing Data: cdssupport@ihsmarkit.com EBS (Formerly known as DeltaOne): DeltaOneSupport@ihsmarkit.com OTC Derivatives Data: OTCDD@spglobal.com CDS Reference Data: red@spglobal.com Iboxx Indices: indices@ihsmarkit.com Cameron Lounsbery (Director - Account Management) Email: Cameron.Lounsbery@spglobal.com Phone: (416)304-6587 | AL30: V11_ITRAXX-SOVX_Red_Indices_YYYYMMDD.xml | AM30: GoldenSource Security Reference Pipeline | AN30: T+1 | AO30: T+1 | AP30: T+1 | AQ30: T+1 | AR30: T+1 | AS30: T+1 | AV30: 0.22569444
A31: 19 | B31: Markit Load | C31: Standalone | E31: Standalone | F31: Price Master | H31: GC | J31: Markit Silver Prices - Price Denorm - Price Publishing | K31: Price Publishing | L31: Please remove this line - replaced by 11.1 | N31: 0.20833333 | P31: =N31+(Summary!$C$30)/24 -> 0.60416667 | Q31: T+1 | T31: Daily(Tue-Sat) | AD31: 0.1875 | AH31: Workflow fail Alert Load Alert - GS MS Only | AV31: 0
C32: Standalone | E32: Standalone | F32: Price Master | G32: HOOPP_PricePublishing_ReconMismatch | H32: GC | J32: WM and Makit CDX Silver Prices - Price Publishing | K32: Price Publishing | N32: 0.21875 | T32: Daily(Tue-Sat) | AM32: GoldenSource Market Data Solution Hub Pipeline | AN32: T+1 | AO32: T+1 | AP32: T+1 | AQ32: T+1 | AR32: T+1 | AS32: T+1
C33: Standalone | E33: Standalone | F33: Price Master | G33: HOOPP_PricePublishing_ReconMismatch_Monday | H33: GC | J33: Makit CDX Silver Prices - Price Publishing | K33: Price Publishing | N33: 0.21875 | T33: Mon | AM33: GoldenSource Market Data Solution Hub Pipeline | AN33: T+1 | AO33: T+1 | AP33: T+1 | AQ33: T+1 | AR33: T+1 | AS33: T+1
A34: 20 | G34: HOOPP_SnP_Full_FileLoad RATINGS_FULL | H34: GC | J34: FileLoad | K34: S&P Ratings (Issue & issuer) - Weekly Full | L34: spInstrumentToEntity20240915091505.entity spAssessmentData20240915091505.entity spRatingData20240915091505.entity spInstrumentToEntity20240915091505.security spAssessmentData20240915091505.security spRatingData20240915091505.security spSecurityLevelData20240915091505.security spInstrumentToEntity20240915091505.final spRatingData20240915091505.final spSecurityLevelData20240915091505.final spAssessmentData20240915091505.final | N34: 0.25 | O34: =N34 + TIME(2, 0, 0) -> 0.33333333 | P34: =N34+(Summary!$C$30)/24 -> 0.64583333 | Q34: T+1 | R34: Every 10 mins | S34: 21 mins | T34: Sun | AD34: 0.27083333 | AE34: 0.29166667 | AH34: File Load Alert - GS MS Only (GS to chase Vendor directly) SLO Alert - GS MS, HOOPP | AI34: Product.Notification <Product.Notification@spglobal.com> | AL34: spInstrumentToEntityYYYYMMDD??????.entity | AM34: GoldenSource Security Reference Pipeline | AN34: T | AU34: T | AV34: 0.29861111
A35: 39 | C35: Standalone | E35: Standalone | G35: HOOPP_WM_FileLoad | H35: GC | J35: FileLoad | K35: WMR | L35: wmr1911.csv rusd19112024.csv | N35: 0.47916667 | O35: =N35 + TIME(2, 0, 0) -> 0.5625 | T35: Daily(Mon-Fri) | U35: WM_HOLIDAY | AD35: 0.5 | AE35: 0.51041667 | AG35: HOOPP_WM_FileLoad | AI35: wmr.ops <wmr.ops@lseg.com> wmr.ops@mrelay.lseg.com | AV35: 0.51041667
A36: 39.1 | B36: 39 | C36: Standalone | E36: Standalone | F36: Price Master | H36: GC | J36: WM Silver Prices - Price Denorm - Price Publishing | K36: Price Publishing | L36: rusdDDMMYYYY_preprocessed.csv wmrDDMM_preprocessed.csv | N36: 0.47916667 | T36: Daily(Mon-Fri) | U36: WM_HOLIDAY | AD36: 0.5 | AE36: 0.51041667 | AG36: HOOPP_WM_FileLoad | AI36: wmr.ops <wmr.ops@lseg.com> wmr.ops@mrelay.lseg.com | AL36: wmrDDMM_preprocessed.csv | AM36: GoldenSource Market Data Solution Hub Pipeline | AN36: T | AO36: T | AP36: T | AQ36: T | AR36: T | AS36: T | AV36: 0.51736111
A37: 21 | C37: Standalone | E37: Standalone | G37: HOOPP_SCD_3PM_FileLoad | H37: GC | J37: FileLoad | K37: Simcorp | L37: SCD_SMF_280824150141.csv | N37: 0.625 | O37: =N37 + TIME(2, 0, 0) -> 0.70833333 | P37: =N37+(Summary!$C$30)/24 -> 1.0208333 | Q37: T | R37: Every 3 mins | S37: 10 mins | T37: Daily(Mon-Fri) | Z37: This SMF load is used for SVC price workflow. 3:10PM SMF load does not exist in PACE current state | AB37: Y | AD37: 0.64583333 | AE37: 0.66666667 | AG37: HOOPP_SCD_3PM_FileLoad | AH37: File Load Alert - GS MS Only (GS to chase Vendor directly) SLO Alert - GS MS, HOOPP | AI37: DXC Overnight Tier 1 <dxcovernighttier1@hoopp.com>; Golden Source Operations <goldensourceoperations@hoopp.com>; ISG-DTS-Operations <isg-dts-operations@hoopp.com> | AJ37: e.g. alert after 1 hour, send email, fail job, run job anyway, etc. | AV37: 0.66666667
A38: 22 | F38: Price Master | G38: HOOPP_BB_FX_REQ_Schedule | H38: GC | J38: BB Request | K38: BB Followon Request FXSOI | L38: GS.BB.FX.out.20240828 | N38: 0.66666667 | P38: =N38+(Summary!$C$30)/24 -> 1.0625 | Q38: T | R38: Every 1 min | S38: 2 mins | T38: Daily(Mon-Fri) | Z38: FX rate request to Bloomberg | AA38: REQUEST.BBPS_FX | AB38: Y | AD38: 0.71875 | AH38: File Load Alert - GS MS Only (GS to chase Vendor directly) SLO Alert - GS MS, HOOPP | AI38: http://service.bloomberg.com Urgent issues: 1-212-617-4390 Global Technical Support: 1-212-318-2000; DXC Contact: DXC Overnight Tier 1 <dxcovernighttier1@hoopp.com> | AV38: 0
A39: 23 | B39: 22 | C39: Chain | E39: HOOPP_BB_FX_Resp_Schedule | F39: Price Master | G39: HOOPP_BB_Trig_FX_FileLoad | H39: GC | J39: FileLoad | K39: BB Followon Response FXSOI | L39: GS.BB.FX.out.20240828 | N39: 0.70833333 | P39: =N39+(Summary!$C$30)/24 -> 1.1041667 | Q39: T | T39: Daily(Mon-Fri) | V39: HOOPP_EVT_BBScheduledResponseWrapper | W39: HOOPP_BB_Trig_FX_FileLoad.json | Z39: FX rate return from Bloomberg | AA39: RETURN.BBPS_FX | AB39: Y | AD39: 0.71875 | AE39: 0.72916667 | AG39: HOOPP_BB_FX_Resp_Schedule | AH39: File Load Alert - GS MS Only (GS to chase Vendor directly) SLO Alert - GS MS, HOOPP | AI39: http://service.bloomberg.com Urgent issues: 1-212-617-4390 Global Technical Support: 1-212-318-2000; DXC Contact: DXC Overnight Tier 1 <dxcovernighttier1@hoopp.com> | AV39: 0.72916667
A40: 24 | B40: 23 | C40: Chain | E40: HOOPP_BB_FX_Resp_Schedule | F40: Price Master | H40: GC | J40: Pricing (Validation) | K40: Final FX Price Validation + Publishing | L40: GS.BB.FX.out.20250128 | N40: 0.70833333 | P40: =N40+(Summary!$C$30)/24 -> 1.1041667 | Q40: T | T40: Daily(Mon-Fri) | AB40: Y | AD40: 0.71875 | AE40: 0.72916667 | AG40: HOOPP_BB_FX_Resp_Schedule | AH40: File Load Alert - GS MS Only (GS to chase Vendor directly) SLO Alert - GS MS, HOOPP | AI40: http://service.bloomberg.com Urgent issues: 1-212-617-4390 Global Technical Support: 1-212-318-2000; DXC Contact: DXC Overnight Tier 1 <dxcovernighttier1@hoopp.com> | AJ40: URGENT TIME CRITICAL PUBLISH TO SF Assumption is that GS will only publish the validated prices | AL40: GS.BB.FX.out.YYYYMMDD | AM40: GoldenSource Market Data Solution Hub Pipeline | AN40: T | AO40: T | AP40: T | AQ40: T | AR40: T | AS40: T | AV40: 0.73611111
A41: 25 | C41: Standalone | D41: BONDS | E41: Standalone | F41: Price Master | G41: HOOPP_FTSE_FileLoad | H41: GC | J41: FileLoad | K41: FTSE | L41: idxdetail_dbi_uo_20240828.csv scmmkt_20240828.csv idxsummary_dbi_20240828.csv idxsummary_rrbi_20240828.csv idxdetail_dbi_tr_20240828.csv idxdetail_rrbi_tr_20240828.csv idxdetail_rrbi_uo_20240828.csv Calculate Fund EOD Performance | N41: 0.75 | O41: =N41 + TIME(2, 0, 0) -> 0.83333333 | P41: =N41+(Summary!$C$30)/24 -> 1.1458333 | Q41: T | R41: Every 10 mins | S41: 21 mins | T41: Daily(Mon-Fri) | U41: CAD1STOCKMARKET | AB41: Y | AD41: 0.79166667 | AE41: 0.8125 | AG41: HOOPP_FTSE_FileLoad | AH41: File Load Alert - GS MS Only (GS to chase Vendor directly) SLO Alert - GS MS, HOOPP | AI41: PC-Bond Index Team <pcbond@FTSERussell.com> Always CC: Info@ftserussell.com Front Desk: Phone: 1-866-551-0617 | AJ41: Incase FTSE/SVC file is delayed and HOOPP_PricePublishing_Bonds has already ran. We need to clean ISPS/GPCS and re run the HOOPP_PricePublishing_Bonds job to generate and publish Golden Prices for FI. | AL41: idxsummary_dbi_YYYYMMDD.csv | AM41: GoldenSource Security Reference Pipeline | AN41: T | AO41: T | AP41: T | AQ41: T | AR41: T | AS41: T | AV41: 0.81944444
A42: 26 | G42: HOOPP_SnP_TSX_FileLoad | H42: GC | J42: FileLoad | K42: S&P TSX | L42: 20240827_60CRX.SDL 20240827_60RX.SDL 20240827_JX.SDL 20240827_SPRTCM.SDL 20240827_SPRTRE.SDL 20240827_SPT60C.SDL 20240827_SPTCFFCP.SDL 20240827_SPTSCECP.SDL 20240827_SPTRED.SDL 20240827_SPTSE.SDL 20240827_SPTSEM.SDL 20240827_SPTSES.SDL 20240827_SPTSETCP.SDL 20240827_SPTSSES.SDL 20240827_SPTSX.SDL 20240827_SPTTCD.SDL 20240827_SPTTCS.SDL 20240827_SPTTEN.SDL 20240827_SPTTFS.SDL 20240827_SPTTMT.SDL 20240827_SPTTHC.SDL 20240827_SPTTIN.SDL 20240827_SPTTRE.SDL 20240827_SPTTTS.SDL 20240827_SPTTTK.SDL 20240827_SPTTUT.SDL 20240827_SPTXDFCP.SDL 20240827_SPTXEDCP.SDL 20240827_TSCE.SDL 20240827_T300C.SDL 20240827_TSXVIX.SDL 20240827_TXCT.SDL 20240827_TXDC.SDL 20240827_TXBB.SDL 20240827_TXCE.SDL 20240827_TXDE.SDL 20240827_TXDV.SDL 20240827_TXEI.SDL 20240827_TXEV.SDL 20240827_TXFF.SDL 20240827_TXEW.SDL 20240827_TXHB.SDL 20240827_TXEVLQ.SDL 20240827_TXIE.SDL 20240827_TXHE.SDL 20240827_TXLVHD.SDL 20240827_TXLV.SDL 20240827_TXOE.SDL 20240827_TXPR.SDL 20240827_TXMLQ.SDL 20240827_TXM.SDL 20240827_TXQLQ.SDL 20240827_TXQ.SDL 20240827_TXRE.SDL 20240827_TXSI.SDL 20240827_XECE.SDL 20240827_TXVHQ.SDL 20240827_TXT1.SDL 20240827_SPTSEM_CLS.SDC 20240827_SPTSES_CLS.SDC 20240827_SPTSE_CLS.SDC 20240827_SPTSSES_CLS.SDC 20240827_SPTTCD_CLS.SDC 20240827_SPTTCS_CLS.SDC 20240827_SPTTEN_CLS.SDC 20240827_SPTTFS_CLS.SDC 20240827_SPTTHC_CLS.SDC 20240827_SPTTIN_CLS.SDC 20240827_SPTTMT_CLS.SDC 20240827_SPTTRE_CLS.SDC 20240827_SPTTTK_CLS.SDC 20240827_SPTTTS_CLS.SDC 20240827_SPTTUT_CLS.SDC 20240827_TXCE_CLS.SDC 20240827_TXDE_CLS.SDC 20240827_TXEW_CLS.SDC 20240827_TXIE_CLS.SDC 20240827_TXOE_CLS.SDC | N42: 0.75 | O42: =N42 + TIME(2, 0, 0) -> 0.83333333 | P42: =N42+(Summary!$C$30)/24 -> 1.1458333 | Q42: T | R42: Every 10 mins | S42: 41 mins | T42: Daily(Mon-Fri) | U42: CAD1STOCKMARKET | Z42: Index data - Back Office file. Not based on any SOI | AB42: Y | AD42: 0.79166667 | AE42: 0.8125 | AG42: HOOPP_SnP_TSX_FileLoad | AH42: File Load Alert - GS MS Only (GS to chase Vendor directly) SLO Alert - GS MS, HOOPP | AI42: Index_services@spdji.com index_services@spglobal.com Phone: 1-212-438-2046 | AL42: YYYYMMDD_SPTSE_CLS.SDC | AM42: GoldenSource Security Reference Pipeline | AN42: T | AO42: T | AP42: T | AQ42: T | AR42: T | AS42: T | AV42: 0.81944444
A43: 27 | G43: HOOPP_SnP_500_FileLoad | H43: GC | J43: FileLoad | K43: S&P 500 | L43: 20240827_SP500.SDL 20240827_SP500_CLS.SDC | N43: 0.75 | O43: =N43 + TIME(2, 0, 0) -> 0.83333333 | P43: =N43+(Summary!$C$30)/24 -> 1.1458333 | Q43: T | R43: Every 10 mins | S43: 21 mins | T43: Daily(Mon-Fri) | U43: US1STOCKMARKET | Z43: Index constituents - - Back Office file. Not based on any SOI | AB43: Y | AD43: 0.77083333 | AE43: 0.78125 | AG43: HOOPP_SnP_500_FileLoad | AH43: File Load Alert - GS MS Only (GS to chase Vendor directly) SLO Alert - GS MS, HOOPP | AI43: Index_services@spdji.com index_services@spglobal.com Phone: 1-212-438-2046 | AL43: YYYYMMDD_SP500_CLS.SDC | AM43: GoldenSource Security Reference Pipeline | AN43: T | AO43: T | AP43: T | AQ43: T | AR43: T | AS43: T | AV43: 0.78819444
A44: 28 | C44: Standalone | E44: Standalone | G44: HOOPP_SCD_6PM_FileLoad | H44: GC | J44: FileLoad | K44: Simcorp | L44: SCD_SMF_280824180126.csv | N44: 0.75 | O44: =N44 + TIME(2, 0, 0) -> 0.83333333 | P44: =N44+(Summary!$C$30)/24 -> 1.1458333 | Q44: T | R44: Every 3 mins | S44: 10 mins | Z44: This SMF load is used for 6PM SVC price workflow. | AA44: SCD.PACE.REFRESH.EARLY | AB44: Y | AD44: 0.77083333 | AE44: 0.79166667 | AG44: HOOPP_SCD_6PM_FileLoad | AH44: File Load Alert - GS MS Only (GS to chase Vendor directly) SLO Alert - GS MS, HOOPP | AI44: DXC Overnight Tier 1 <dxcovernighttier1@hoopp.com>; Golden Source Operations <goldensourceoperations@hoopp.com>; ISG-DTS-Operations <isg-dts-operations@hoopp.com> | AV44: 0.79166667
B45: 28 | E45: Standalone | G45: HOOPP_SVC_SOI_PricingRequest_Fileload | H45: GC | J45: Request | K45: SVC Request File | L45: SCD_SVC_REQ_TEST_*.txt | N45: ~18:30 | T45: Daily(Mon-Fri) | AI45: Vendor Technical Contact: dco@ssnc.com SVC-ClientSupport@sscinc.com Vendor Business Contact: Portch, Glenn <gportch@sscinc.com> Garito, Nick <ngarito@sscinc.com> Martinis, Peter pmartinis@sscinc.com call 905 629-8000 and choose prompt #1, then prompt #7 for SVC | AV45: #VALUE!
A46: 29 | B46: 28 | G46: HOOPP_BB_Generic_EOD_Req_Schedule | H46: GC | J46: BB Request | K46: BB Followon Request Generic | L46: GS.BB.EOD.GENERIC.out.20240828 | N46: 0.78125 | P46: =N46+(Summary!$C$30)/24 -> 1.1770833 | Q46: T | T46: Daily(Mon-Fri) | Z46: FX rate request to Bloomberg | AA46: REQUEST.BBPS_FX | AB46: Y | AD46: 0.79166667 | AH46: File Load Alert - GS MS Only (GS to chase Vendor directly) SLO Alert - GS MS, HOOPP | AI46: http://service.bloomberg.com Urgent issues: 1-212-617-4390 Global Technical Support: 1-212-318-2000 | AV46: 0
A47: 30 | B47: 29 | G47: HOOPP_BB_Generic_EOD_Resp_Schedule | H47: GC | J47: FileLoad | K47: BB Followon Response Generic | L47: GS.BB.EOD.GENERIC.out.20240828 | N47: 0.79166667 | P47: =N47+(Summary!$C$30)/24 -> 1.1875 | Q47: T | T47: Daily(Mon-Fri) | V47: HOOPP_EVT_BBScheduledResponseWrapper | W47: HOOPP_BB_Trig_FX_FileLoad.json | Z47: FX rate return from Bloomberg | AA47: RETURN.BBPS_FX | AB47: Y | AD47: 0.80208333 | AE47: 0.83333333 | AG47: HOOPP_BB_Generic_EOD_Resp_Schedule | AH47: File Load Alert - GS MS Only (GS to chase Vendor directly) SLO Alert - GS MS, HOOPP | AI47: http://service.bloomberg.com Urgent issues: 1-212-617-4390 Global Technical Support: 1-212-318-2000 | AV47: 0.83333333
A48: 31 | C48: Standalone | D48: BONDS | E48: Standalone | F48: Price Master | G48: HOOPP_SVC_FileLoad | H48: GC | J48: FileLoad | K48: SVC Response (PRT, INACTIVE, PRICE,UNMATCHED) | L48: SCD_SVC_PRT_240828.TXT SCD_SVC_PRICE_240828.TXT SCD_SVC_UNMATCHED_240828.TXT SCD_SVC_INACTIVE_240828.TXT | N48: 0.79166667 | O48: =N48 + TIME(2, 0, 0) -> 0.875 | P48: =N48+(Summary!$C$30)/24 -> 1.1875 | Q48: T | R48: Every 5 mins | S48: 16 mins | T48: Daily(Mon-Fri) | U48: SVC_HOLIDAY | AB48: Y | AD48: 0.8125 | AE48: 0.83333333 | AG48: HOOPP_SVC_FileLoad | AH48: File Load Alert - GS MS Only (GS to chase Vendor directly) SLO Alert - GS MS, HOOPP | AI48: dco@ssnc.com SVC-ClientSupport@sscinc.com Portch, Glenn <gportch@sscinc.com> Garito, Nick <ngarito@sscinc.com> Martinis, Peter pmartinis@sscinc.com call 905 629-8000 and choose prompt #1, then prompt #7 for SVC | AJ48: Incase FTSE/SVC file is delayed and HOOPP_PricePublishing_Bonds has already ran. We need to clean ISPS/GPCS and re run the HOOPP_PricePublishing_Bonds job to generate and publish Golden Prices for FI. | AV48: 0.83333333
A49: 32 | B49: 30 | G49: HOOPP_BB_MBS_EOD_Req_Schedule | H49: GC | J49: BB Request | K49: BB Followon Request MBS | L49: GS.BB.MBS.out.20240828 | N49: 0.80208333 | P49: =N49+(Summary!$C$30)/24 -> 1.1979167 | Q49: T | T49: Daily(Mon-Fri) | Z49: FX rate request to Bloomberg | AA49: REQUEST.BBPS_FX | AB49: Y | AD49: 0.8125 | AH49: File Load Alert - GS MS Only (GS to chase Vendor directly) SLO Alert - GS MS, HOOPP | AI49: http://service.bloomberg.com Urgent issues: 1-212-617-4390 Global Technical Support: 1-212-318-2000 | AV49: 0
A50: 33 | B50: 32 | G50: HOOPP_BB_MBS_EOD_Resp_Schedule | H50: GC | J50: FileLoad | K50: BB Followon Response MBS | L50: GS.BB.MBS.out.20240828 | N50: 0.8125 | P50: =N50+(Summary!$C$30)/24 -> 1.2083333 | Q50: T | T50: Daily(Mon-Fri) | V50: HOOPP_EVT_BBScheduledResponseWrapper | W50: HOOPP_BB_Trig_FX_FileLoad.json | Z50: FX rate return from Bloomberg | AA50: RETURN.BBPS_FX | AB50: Y | AD50: 0.82291667 | AE50: 0.83333333 | AG50: HOOPP_BB_MBS_EOD_Resp_Schedule | AH50: File Load Alert - GS MS Only (GS to chase Vendor directly) SLO Alert - GS MS, HOOPP | AI50: http://service.bloomberg.com Urgent issues: 1-212-617-4390 Global Technical Support: 1-212-318-2000 | AL50: GS.BB.MBS.out.YYYYMMDD | AM50: GoldenSource Security Reference Pipeline | AN50: T | AO50: T | AP50: T | AQ50: T | AR50: T | AS50: T | AV50: 0.84027778
A51: 34 | B51: 25,31 | D51: BONDS | F51: Price Master | G51: HOOPP_PricePublishing_Bonds | J51: FTSE/SVC Silver + Bonds Gold Prices - Price Validation - Price Denorm - Price Publishing | K51: Price Publishing | N51: 0.82291667 | P51: =N51+(Summary!$C$30)/24 -> 1.21875 | Q51: T | T51: Daily(Mon-Fri) | U51: SVC_HOLIDAY | AB51: Y | AD51: 0.83333333 | AE51: 0.85416667 | AG51: HOOPP_PricePublishing_Bond_Schedule | AJ51: Incase FTSE/SVC file is delayed and HOOPP_PricePublishing_Bonds has already ran. We need to clean ISPS/GPCS and re run the HOOPP_PricePublishing_Bonds job to generate and publish Golden Prices for FI. | AL51: idxsummary_dbi_YYYYMMDD.csv SCD_SVC_PRICE_YYMMDD.TXT | AM51: GoldenSource Market Data Solution Hub Pipeline | AN51: T | AO51: T | AP51: T | AQ51: T | AR51: T | AS51: T | AV51: 0.86111111
A52: 35 | D52: MARKIT | G52: HOOPP_ICE_FileLoad | J52: FileLoad | K52: ICE | L52: ICC_hoopp_FinalEODSettlements_20240820.csv ICC_CDSIndexClearingEligibleInstruments_20240820.csv ICC_CDSSingleNameClearingEligibleInstruments_20240820.csv ICC_hoopp_PositionMTMMarginDetail_20240820.csv | N52: 0.83333333 | O52: 0.91666667 | Q52: T | R52: Every 10 mins | T52: Daily(Mon-Fri) | U52: ICE_LCH_HOLIDAY | AD52: 0.85416667 | AE52: 0.875 | AG52: HOOPP_ICE_FileLoad | AI52: Vendor Technical Contact: Ice: 1-770-999-4501, +44-203-948-6501, +65-6817-6211 ICE Helpdesk (General) Email: sd-suppport@theice.com Phone: Option 5, sub-option 1 For index/constituents file: https://indices.theice.com/ ICE Data Derivatives Support Email: IDDSupport@ice.com Escalation Support Teams: ClientSupport-ICEDataDerivatives-DataAndValuations@theice.com ClientSupport-ICEDataDerivatives-Solutions@theice.com CS Teams Manager: Shira Levy, Manager ICE Data Derivatives Support - Shira.Levy@ice.com For prices file: icelinksupport@theice.com icelinkhelp@theice.com Super D: 8:30am - 10pm EST IDDSupport@ice.com +1 770 999 4501 Option 5 After 10pm (10pm to 8:30am) EMEA/APAC support teams step in until 8:30am EST EMEA/APAC is in the attached document. CS_Escalation_Matrix_By_Region_201902_(003).docx Vendor Business Contact: Owen Magee (Sales Rep) Email: Owen.Magee@ice.com Thomas Cangelosi (Relationship Manager/Account Rep) Email: Tom.Cangelosi@ice.com | AV52: 0.875
A53: 36 | B53: 36 | D53: MARKIT | F53: Price Master | J53: ICE Price Publishing (Gold + Silver) - Price Derivation - Price Valication - Price Denorm - Price Publishing | K53: Price Publishing | L53: Silver for CC_CDS, CC_CDX_CDS and ICE_SOI Gold prices for CC_CDS | N53: 0.84375 | T53: Daily(Mon-Fri) | AD53: 0.85416667 | AE53: 0.875 | AG53: HOOPP_PricePublishing_MarkitSOI_CC_CDX_CDS_ICE | AL53: ICC_hoopp_FinalEODSettlements_YYYYMMDD.csv | AM53: GoldenSource Market Data Solution Hub Pipeline | AN53: T | AO53: T | AP53: T | AQ53: T | AR53: T | AS53: T | AV53: 0.88194444
A54: 37 | C54: Standalone | E54: Standalone | G54: HOOPP_LCH_FileLoad | H54: GC | J54: FileLoad | K54: LCH | L54: P-PSWC-HOOPPXXX_FDM-20240904-015042_20240904_REP000F1e - Trade Level Pricing_ 1.TXT | N54: 0.84375 | O54: 0.97916667 | Q54: T | R54: Every 10 mins | T54: Daily(Mon-Fri) | U54: ICE_LCH_HOLIDAY | AD54: 0.90625 | AE54: 0.91666667 | AG54: HOOPP_LCH_FileLoad | AI54: Vendor Technical Contact: ratesclientservices@lch.com SwapClear.ClientOnboarding@lch.com Vendor Business Contact: Christopher.Licini@lch.com | AV54: 0.91666667
B55: 37 | F55: Price Master | J55: LCH Price Publishing (Gold + Silver) - Price Derivation - Price Valication - Price Denorm - Price Publishing | K55: Price Publishing | L55: LCH_SOI | N55: 0.84375 | T55: Daily(Mon-Fri) | U55: ICE_LCH_HOLIDAY | AD55: 0.90625 | AE55: 0.91666667 | AG55: HOOPP_LCH_FileLoad | AL55: P-PSWC-HOOPPXXX_FDM-YYYYMMDD-??????_YYYYMMDD_REP000F1e%20-%20Trade%20Level%20Pricing_%201.TXT | AM55: GoldenSource Market Data Solution Hub Pipeline | AN55: T | AO55: T | AP55: T | AQ55: T | AR55: T | AS55: T | AV55: 0.92361111
B56: 28 | C56: Standalone | E56: Standalone | G56: HOOPP_Markit_OTC_Request_Fileload | H56: GC | J56: Request | K56: Markit OTC Request File | L56: TrancheCDSMarkITRequest_03042025.xml CDSOptionsMarkITRequest_03042025.xml CDSIndexMarkITRequest_03042025.xml ABXCreditIndexMarkITRequest_03042025.xml | N56: ~18:30 | T56: Daily(Mon-Fri) | AI56: Vendor Technical Contact: General support@spglobal.com index_services@spglobal.com Michael.Stone@ihsmarkit.com For any escalation or urgent request: referencedataclientservice@spglobal.com SFTP issues: data.delivery@ihsmarkit.com CALL THIS NUMBER - GOES TO ALL INDIA SUPPORT STAFF: +91 120 611 8051 MK-ValHOOPP@ihsmarkit.com Kamal.Sehgal@ihsmarkit.com Vrinda.Pal@ihsmarkit.com Managers: Sachin.Singhal@ihsmarkit.com Rajesh.Kumar2@ihsmarkit.com Toronto Staff: spencer.wiseman@ihsmarkit.com Abhinit.Kumar@ihsmarkit.com Red red@spglobal.com support@spglobal.com Markit Vol OTCDD@spglobal.com After Hours support: +1 877 762 7548 Corporate Action markitcorporateactions@ihsmarkit.com managedcorporateactions@ihsmarkit.com support@markit.com PE Vals (related to CIFC) MK-PEHOOPP@ihsmarkit.com DL-PE-PEValsSupport@ihsmarkit.com Ashwani.Rai@ihsmarkit.com Vendor Business Contact: Lucas Pettella's Team - 1st point of contact Portfolio Valuation: MK-ValHOOPP@ihsmarkit.com (sydney.workman@spglobal.com, nikita.zinchenko@spglobal.com) CDS Pricing Data: cdssupport@ihsmarkit.com EBS (Formerly known as DeltaOne): DeltaOneSupport@ihsmarkit.com OTC Derivatives Data: OTCDD@spglobal.com CDS Reference Data: red@spglobal.com Iboxx Indices: indices@ihsmarkit.com Cameron Lounsbery (Director - Account Management) Email: Cameron.Lounsbery@spglobal.com Phone: (416)304-6587 | AV56: 0
A57: 40 | C57: Standalone | E57: Standalone | G57: HOOPP_NT_FileLoad | H57: GC | J57: FileLoad | K57: Northern Trust | L57: SECURITY_MASTER_CSM_20241126_202738.CSV DAILY_TRANSACTIONS_SRD3363_CSM_20241126_202741.CSV | N57: 0.91666667 | O57: 0.041666667 | R57: Every 10 mins | T57: Daily(Mon-Fri) | AD57: 0.9375 | AE57: 0.95833333 | AI57: Broker Files GSL_Production@ntrs.com GSL_Support_Mailbox@ntrs.com Transmissions@ntrs.com | AV57: 0.95833333
A58: 40.1 | B58: 40 | F58: Price Master | G58: HOOPP_NT_FileLoad | J58: NT Silver Prices - Price Denorm - Price Publishing | K58: Price Publishing | L58: NTFX_SOI | N58: 0.91666667 | T58: Daily(Mon-Fri) | AD58: 0.94791667 | AE58: 0.95833333 | AL58: SECURITY_MASTER_CSM_YYYYMMDD_??????.CSV DAILY_TRANSACTIONS_SRD3363_CSM_YYYYMMDD_??????.CSV | AM58: GoldenSource Market Data Solution Hub Pipeline | AN58: T | AO58: T | AP58: T | AQ58: T | AR58: T | AS58: T | AV58: 0.96527778
A59: 40 | C59: Standalone | E59: Standalone | G59: HOOPP_NT_POSandCol_FileLoad | H59: GC | J59: FileLoad | K59: Northern Trust | L59: DAILY_POSITIONS_CSM MONTHLY_POSITION_CSM DAILY_TRANSACTIONS_CSM | N59: 0.98958333 | T59: Daily(Mon-Fri) | AD59: 0.041666667 | AE59: 0.041666667 | AG59: HOOPP_NT_FileLoad | AI59: index_services@spglobal.com | AV59: 0.041666667
A60: 40 | C60: Standalone | E60: Standalone | G60: HOOPP_NT_GSL_Schedule | J60: FileLoad | K60: Nothern Trust | L60: DAILY_COLLATERIAL_SRD2904_CSM FMH2956S_GSL_LENDING_REPORT_YYYYYMMDD.TXT | N60: 0.0069444444 | T60: Daily(Tue-Sat) | AD60: 0.1875 | AE60: 0.1875 | AG60: HOOPP_NT_FileLoad | AI60: Transmissions@ntrs.com GSL_Support_Mailbox@ntrs.com GSL_Production@ntrs.com | AV60: 0.1875
A61: 119 | C61: Standalone | E61: Standalone | G61: HOOPP_CoppClark_FileLoad | H61: GC | J61: FileLoad | K61: CoppClark | L61: CenterList_20250103.csv CurrencyPaymentWeekends_20250103.csv CurrencyPaymentHolidays_20250103.csv CurrencyPaymentCenters_20250103.csv ExchangeSettlementHolidays_20250103.csv ExchangeSettlementCenters_20250103.csv CurrencyTradingWorkingWKDs_20250103.csv CurrencyTradingWeekends_20250103.csv CurrencyTradingHolidays_20250103.csv CurrencyTradingCenters_20250103.csv CurrencyPaymentWorkingWKDs_20250103.csv ExchangeTradingHolidays_20250103.csv ExchangeTradingCenters_20250103.csv ExchangeSettlementWorkingWKDs_20250103.csv ExchangeSettlementWeekends_20250103.csv FinancialCenters_20250103.csv ExchangeTradingWorkingWKDs_20250103.csv ExchangeTradingWeekends_20250103.csv WorkingWeekends_20250103.csv | N61: 0.91666667 | T61: Daily(Mon-Sun) | AD61: 0.9375 | AE61: 0.95833333 | AG61: HOOPP_CoppClark_FileLoad | AI61: For any escalation or urgent request: referencedataclientservice@spglobal.com | AV61: 0.95833333
A62: 38 | C62: Standalone | D62: MARKIT | E62: Standalone | G62: HOOPP_MOTC_DAILY_SG_CRED_FileLoad / HOOPP_MOTC_DAILY_SG_CRED_FileLoad_Sunday | H62: GC | J62: FileLoad | K62: Markit OTC Fileload | L62: HOOPP_SG_DAILY_CRED.01Nov24.csv | N62: 0.92708333 | O62: 0.98958333 | R62: Every 10 mins | T62: Daily(Sun-Thu) | U62: MARKIT_HOLIDAY | AD62: 0.95833333 | AE62: 0.96875 | AG62: HOOPP_MOTC_DAILY_SG_CRED_FileLoad | AI62: SFTP issues: data.delivery@ihsmarkit.com | AV62: 0.96875
A63: 38.1 | B63: 36 | D63: MARKIT | E63: HOOPP_PricePublishing_OTC_DAILY_CRED | F63: Price Master | J63: Markit OTC Price Publishing (Silver) - Price Denorm - Price Publishing | K63: Price Publishing | L63: HOOPP_SG_DAILY_CRED (silver prices only) | N63: 0.92708333 | T63: Daily(Sun-Thu) | U63: MARKIT_HOLIDAY | AD63: 0.95833333 | AE63: 0.96875 | AG63: HOOPP_PricePublishing_OTC_DAILY_CRED | AL63: HOOPP_SG_DAILY_CRED.DDMonYY.csv | AM63: GoldenSource Market Data Solution Hub Pipeline | AN63: T | AO63: T | AP63: T | AQ63: T | AR63: T | AS63: T+2 | AV63: 0.97569444
A64: 31 | C64: Standalone | E64: Standalone | G64: HOOPP_SCD_11PM_FileLoad | H64: GC | J64: FileLoad | K64: Simcorp | L64: SCD_SMF_280824230117.csv | N64: 0.95833333 | O64: =N64 + TIME(2, 0, 0) -> 1.0416667 | P64: =N64+(Summary!$C$30)/24 -> 1.3541667 | Q64: T | R64: Every 3 mins | S64: 10 mins | Z64: HOOP_SOI | AB64: Y | AD64: 0.97916667 | AE64: 0 | AG64: HOOPP_SCD_11PM_FileLoad | AH64: File Load Alert - GS MS Only (GS to chase Vendor directly) SLO Alert - GS MS, HOOPP | AI64: DXC Overnight Tier 1 <dxcovernighttier1@hoopp.com>; Golden Source Operations <goldensourceoperations@hoopp.com>; ISG-DTS-Operations <isg-dts-operations@hoopp.com> | AL64: SCD_SMF_DDMMYY??????.csv | AM64: GoldenSource Security Reference Pipeline | AN64: T | AO64: T | AP64: T | AQ64: T | AR64: T | AS64: T | AV64: 0.0069444444
A65: 32 | C65: Standalone | E65: Standalone | G65: HOOPP_SnP_FileLoad RATINGS_DELTA | H65: GC | J65: FileLoad | K65: S&P Ratings (Issue & issuer) - Delta | L65: spInstrumentToEntity20240828185719-001.security spAssessmentData20240828185719-001.security spSecurityLevelData20240828185719-001.security spRatingData20240828185719-001.security | N65: 0.97916667 | O65: =N65 + TIME(2, 0, 0) -> 1.0625 | P65: =N65+(Summary!$C$30)/24 -> 1.375 | Q65: T | R65: Every 10 mins | S65: 21 mins | T65: Daily(Mon-Fri) | Z65: Rating load - backoffice file, not dependent on SOI | AB65: Y | AD65: 0.99930556 | AE65: 0.052083333 | AG65: RATINGS_DELTA | AH65: File Load Alert - GS MS Only (GS to chase Vendor directly) SLO Alert - GS MS, HOOPP | AI65: Product.Notification <Product.Notification@spglobal.com> | AJ65: What is the schedule for spInstrumentToEntity20240904185714-001.entity? We see loads at 1130pm and 8am for 1 hour. Can you please keep schedule to non business hours - 11pm on T works. | AL65: spInstrumentToEntityYYYYMMDD??????-001.entity | AM65: GoldenSource Security Reference Pipeline | AN65: T | AO65: T | AP65: T | AQ65: T | AR65: T | AS65: T | AV65: 0.059027778
A66: 41 | C66: Standalone | E66: Standalone | G66: HOOPP_BF_TD_FileLoad | J66: Broker Files | K66: TD | L66: tdsi_hoopp_loan_fees_03 Account_07-08-2024.csv TD position file_07-08-2024.csv | N66: 0.33333333 | O66: 0.4375 | R66: Every 10 mins | T66: Daily(Mon-Fri) | AD66: 0.4375 | AE66: 0.4375 | AI66: Kamal.Sehgal@ihsmarkit.com
A67: 42.1 | C67: Standalone | E67: Standalone | G67: HOOPP_BF_CIBC_FileLoad | J67: Broker Files | K67: CIBC | L67: cibc_hoopp_fee_20240709.csv cibc_hoopp_fee_20240709.csv | N67: 0.33333333 | O67: 0.4375 | R67: Every 10 mins | T67: Daily(Tue-Fri) | AD67: 0.4375 | AE67: 0.4375 | AI67: Vrinda.Pal@ihsmarkit.com
A68: 42.2 | C68: Standalone | E68: Standalone | G68: HOOPP_BF_CIBC_FileLoad | J68: Broker Files | K68: CIBC | L68: cibc_hoopp_fee_20240709.csv cibc_hoopp_fee_20240709.csv | N68: 0.8125 | O68: 0.91666667 | R68: Every 10 mins | T68: Weekly(Sat) | AD68: 0.4375 | AE68: 0.4375 | AI68: Vrinda.Pal@ihsmarkit.com
A69: 42 | C69: Standalone | E69: Standalone | G69: HOOPP_BF_CIBCWM_FileLoad | J69: Broker Files | K69: CIBCWM | L69: HOOPP Collateral_20240806.txt HOOPP Loans_20250212.txt | N69: 0.33333333 | O69: 0.4375 | R69: Every 10 mins | T69: Daily(Mon-Fri) | AD69: 0.4375 | AE69: 0.4375 | AI69: Sachin.Singhal@ihsmarkit.com
A70: 43 | C70: Standalone | E70: Standalone | G70: HOOPP_BF_RBCDS_FileLoad | J70: Broker Files | K70: RBC | L70: RBCDS_FEE_HOOPP_20240710.csv RBCDS_POS_HOOPP_20240710.txt | N70: 0.47916667 | R70: Every 10 mins | T70: Daily(Mon-Fri) | AD70: 0.4375 | AE70: 0.4375 | AI70: Rajesh.Kumar2@ihsmarkit.com
A71: 44 | C71: Standalone | E71: Standalone | G71: HOOPP_BF_RTD_FileLoad | J71: Broker Files | K71: RBC Dexia | L71: RBCIS_POS_HOOP_20241002.TXT | N71: 0.33333333 | O71: 0.4375 | R71: Every 10 mins | T71: Daily(Tue-Sat) | AD71: 0.4375 | AE71: 0.4375 | AI71: RBC Investor & Treasury Services (RBC IS) slcs@rbc.com birju.sheth@rbc.com (New workflow) arif.saiyed@rbc.com (New workflow)
A72: 45 | C72: Standalone | E72: Standalone | G72: HOOPP_BF_GS_FileLoad | J72: Broker Files | K72: Goldman Sachs | L72: HOOPP Recon 2024-07-08.csv | N72: 0.83333333 | Q72: T | R72: Every 10 mins | T72: Daily(Mon-Fri) | AD72: 0.4375 | AE72: 0.4375 | AI72: spencer.wiseman@ihsmarkit.com
A73: 46 | C73: Standalone | E73: Standalone | G73: HOOPP_BF_BMO_FileLoad | J73: Broker Files | K73: BMO | L73: bmo_hoopp_pos_20240705.csv | N73: 0.95833333 | Q73: T | R73: Every 10 mins | T73: Daily(Tue-Sat) | AD73: 0.4375 | AE73: 0.4375 | AI73: Abhinit.Kumar@ihsmarkit.com
A74: 47 | C74: Standalone | E74: Standalone | G74: HOOPP_BF_Natixis_FileLoad | J74: Broker Files | K74: Natixis | L74: LoanetHooppReport_20240708.csv.gpg | N74: 0.33333333 | O74: 0.4375 | R74: Every 10 mins | T74: Daily(Mon-Fri) | AD74: 0.4375 | AE74: 0.4375 | AI74: Vendor Technical Contact: DTTransversalITApplicationSupport@natixis.com uscibusitapplicationdevtequities@natixis.com Vendor Business Contact: charles.luo@natixis.com USCIBSecuritieslending@natixis.com OpsStockLoan@natixis.com carol.amandola-ext@natixis.com
A75: 48.1 | C75: Standalone | E75: Standalone | G75: HOOPP_BF_SCM_FileLoad | J75: Broker Files | K75: Scotia | L75: HOOPPS.SCM_FEE_HOOPP_20240708.TXT HOOPPS.SCM_POS_HOOPP_20240708.TXT | N75: 0.33333333 | O75: 0.4375 | R75: Every 10 mins | T75: Daily(Tue-Fri) | AD75: 0.4375 | AE75: 0.4375 | AI75: StockLoan.SupportRim@scotiabank.com stockloan.ba@scotiabank.com getgo.support@scotiabank.com
A76: 48.2 | C76: Standalone | E76: Standalone | G76: HOOPP_BF_SCM_FileLoad | J76: Broker Files | K76: Scotia | L76: HOOPPS.SCM_FEE_HOOPP_20240708.TXT HOOPPS.SCM_POS_HOOPP_20240708.TXT | N76: 0.54166667 | O76: 0.64583333 | R76: Every 10 mins | T76: Weekly(Sat) | AD76: 0.4375 | AE76: 0.4375 | AI76: StockLoan.SupportRim@scotiabank.com stockloan.ba@scotiabank.com getgo.support@scotiabank.com
A77: 49 | C77: Standalone | E77: Standalone | G77: HOOPP_BF_NT_FileLoad | J77: Broker Files | K77: Nothern Trust | L77: FMH3676S_DAILY_GSL_POSITION_FILE_20240708.csv | N77: 0.33333333 | O77: 0.4375 | R77: Every 10 mins | T77: Daily(Mon-Fri) | AD77: 0.4375 | AE77: 0.4375 | AI77: support@spglobal.com
A78: 50 | C78: Standalone | E78: Standalone | G78: HOOPP_BF_NATLBK_FileLoad | J78: Broker Files | K78: National Bank | L78: HOOPP_DAILY_20241126.csv | N78: 0.33333333 | O78: 0.4375 | R78: Every 10 mins | T78: Daily(Tue-Sat) | AD78: 0.4375 | AE78: 0.4375 | AI78: Vendor Technical Contact: SBLSettlement@bnc.ca sble4e@nbc.ca sec_lending_it_support@nbf.ca kaki.chan@bnc.ca
A79: AM | AH79: File Load Alert - GS MS Only (GS to chase Vendor directly) SLO Alert - GS MS, HOOPP
A80: 24 | B80: 23 | C80: Chain | E80: HOOPP_BB_FX_Resp_Schedule | F80: Price Master | G80: HOOPP_BB_S3DecryptUpload | H80: GC | J80: Maintenance | Q80: T | T80: Daily(Mon-Fri) | V80: HOOPP_EVT_BB_DecryptUpload | W80: BB_S3DecryptUpload.json | Z80: This job uploads the raw file to S3 bucket | AB80: Y
A81: 25 | B81: 24 | C81: Chain | E81: HOOPP_BB_FX_Resp_Schedule | F81: Price Master | G81: HOOPP_PVC_FX_FileLoad_Job | H81: GC | J81: Pricing (Validation) | Q81: T | T81: Daily(Mon-Fri) | V81: HOOPP_EVT_PriceValidationConsolidated_TDate | W81: PriceValidationConsolidated_FX_SOI.json | AB81: Y
A82: 26 | B82: 25 | C82: Chain | E82: HOOPP_BB_FX_Resp_Schedule | F82: Price Master | G82: HOOPP_PriceDenomSilver_FileLoad_Job | H82: GC | J82: Pricing (Denormalization Silver) | Q82: T | T82: Daily(Mon-Fri) | V82: HOOPP_EVT_PriceDenormalisation_TDate | W82: PriceDenormSilverFX.json | AB82: Y
A83: 27 | B83: 26 | C83: Chain | E83: HOOPP_BB_FX_Resp_Schedule | F83: Price Master | G83: HOOPP_PriceDenomGold_FileLoad_Job | H83: GC | J83: Pricing (Denormalization Golden) | Q83: T | T83: Daily(Mon-Fri) | V83: HOOPP_EVT_PriceDenormalisation_TDate | W83: PriceDenormGoldFX.json
A84: 28 | B84: 27 | C84: Chain | E84: HOOPP_BB_FX_Resp_Schedule | F84: Price Master | G84: HOOPP_CloudPubMDS_PriceSilver_FL - Vendor ID = BB HOOPP_CloudPubMDS_FXPriceSilver_BB | H84: GC | J84: Publishing | Q84: T | T84: Daily(Mon-Fri) | V84: HOOPP_EVT_CloudPublishingMDS_TDate_Wrapper | W84: CloudMDSFXPriceSilver.json
A85: 30 | B85: 29 | C85: Chain | E85: HOOPP_BB_FX_Resp_Schedule | F85: Price Master | G85: HOOPP_CloudPubMDS_PriceGold_FL HOOPP_CloudPubMDS_FXPriceGold_BB | H85: GC | J85: Publishing | Q85: T | T85: Daily(Mon-Fri) | V85: HOOPP_EVT_CloudPublishingMDS_TDate_Wrapper | W85: CloudMDSFXPriceGold.json
A86: 30.1 | B86: 30 | C86: Chain | E86: HOOPP_BB_FX_Resp_Schedule | F86: Price Master | G86: HOOPP_CloudPubMDS_FXWMSOISilver_BB | H86: GC | J86: Publishing | Q86: T | T86: Daily(Mon-Fri) | V86: HOOPP_EVT_CloudPublishingMDS_TDate_Wrapper
A87: 51 | B87: 30 | C87: Chain | E87: HOOPP_PricePublishing_Bond_Schedule | F87: Price Master | G87: HOOPP_PVC_Bond_FileLoad_Job | H87: GC | J87: Pricing (Validation) | Q87: T | T87: Daily(Mon-Fri) | V87: HOOPP_EVT_PriceValidationConsolidated_TDate | W87: PriceValidationConsolidated_FI.json | AB87: Y
A88: 52 | B88: 51 | C88: Chain | E88: HOOPP_PricePublishing_Bond_Schedule | F88: Price Master | G88: HOOPP_PriceDenomBondSilver_Job | H88: GC | J88: Pricing (Denormalization Silver) | Q88: T | T88: Daily(Mon-Fri) | V88: HOOPP_EVT_PriceDenormalisation_TDate | W88: PriceDenormSilver_Bonds.json | AB88: Y
A89: 53 | B89: 52 | C89: Chain | E89: HOOPP_PricePublishing_Bond_Schedule | F89: Price Master | G89: HOOPP_PriceDenomBondGold_Job | H89: GC | J89: Pricing (Denormalization Golden) | Q89: T | T89: Daily(Mon-Fri) | V89: HOOPP_EVT_PriceDenormalisation_TDate | W89: PriceDenormGold_Bonds.json | AB89: Y
A90: 54 | B90: 53 | C90: Chain | E90: HOOPP_PricePublishing_Bond_Schedule | F90: Price Master | G90: HOOPP_CloudPubMDS_BondPriceSilver - Vendor ID = SVC HOOPP_CloudPubMDS_BondPriceSilver_SVC | H90: GC | J90: Publishing | Q90: T | T90: Daily(Mon-Fri) | V90: HOOPP_EVT_CloudPublishingMDS_TDate_Wrapper | W90: CloudMDSBondPriceSilver.json
A91: 56 | B91: 55 | C91: Chain | E91: HOOPP_PricePublishing_Bond_Schedule | F91: Price Master | G91: HOOPP_CloudPubMDS_BondPriceGold | H91: GC | J91: Publishing | Q91: T | T91: Daily(Mon-Fri) | V91: HOOPP_EVT_CloudPublishingMDS_TDate_Wrapper | W91: CloudMDSBondPriceGold.json
A92: 58 | B92: 57 | C92: Chain | E92: HOOPP_PricePublishing_Bond_Schedule | F92: Price Master | G92: HOOPP_CloudPubMDS_FTSEPriceSilver - Vendor ID = FTSEIDX HOOPP_CloudPubMDS_FTSEPriceSilver_FTSEIDX | H92: GC | J92: Publishing | Q92: T | T92: Daily(Mon-Fri) | V92: HOOPP_EVT_CloudPublishingMDS_TDate_Wrapper | W92: CloudMDSFTSEPriceSilver.json
A93: 60 | B93: 59 | C93: Chain | E93: HOOPP_PricePublishing_Bond_Schedule | F93: Price Master | G93: HOOPP_CloudPubMDS_KeyFigures HOOPP_CloudPubMDS_KeyFigures_SVC | H93: GC | J93: Publishing | Q93: T | T93: Daily(Mon-Fri) | V93: HOOPP_EVT_CloudPublishingMDS_TDate_Wrapper | W93: CloudMDS_KF.json
A94: 61 | C94: Chain | E94: HOOPP_PricePublishing_Equity_Schedule | F94: Price Master | G94: HOOPP_PriceDerivation_FileLoad_Job | H94: GC | J94: Pricing (Derivation) | Q94: T+1 | T94: Daily(Tue-Sat) | V94: HOOPP_EVT_PriceDerivation_Wrapper | W94: PriceDerivation.json
A95: 62 | B95: 61 | C95: Chain | E95: HOOPP_PricePublishing_Equity_Schedule | F95: Price Master | G95: HOOPP_PVC_EQ_FileLoad_Job | H95: GC | J95: Pricing (Validation) | Q95: T+1 | T95: Daily(Tue-Sat) | V95: HOOPP_EVT_PriceValidationConsolidated | W95: PriceValidationConsolidated_Equities.json | AB95: Y
A96: 63 | B96: 62 | C96: Chain | E96: HOOPP_PricePublishing_Equity_Schedule | F96: Price Master | G96: HOOPP_PriceDenomEQSilver_Job | H96: GC | J96: Pricing (Denormalization Silver) | Q96: T+1 | T96: Daily(Tue-Sat) | V96: HOOPP_EVT_PriceDenormalisation | W96: PriceDenormSilver_EQ.json | AB96: Y
A97: 64 | B97: 63 | C97: Chain | E97: HOOPP_PricePublishing_Equity_Schedule | F97: Price Master | G97: HOOPP_PriceDenomEQGold_Job | H97: GC | J97: Pricing (Denormalization Golden) | Q97: T+1 | T97: Daily(Tue-Sat) | V97: HOOPP_EVT_PriceDenormalisation | W97: PriceDenormGold_EQ.json | AB97: Y
A98: 65 | B98: 64 | C98: Chain | E98: HOOPP_PricePublishing_Equity_Schedule | F98: Price Master | G98: HOOPP_CloudPubMDS_EquityPriceSilver HOOPP_CloudPubMDS_GENTSOIPriceSilver_BB | H98: GC | J98: Publishing | Q98: T+1 | T98: Daily(Tue-Sat) | V98: HOOPP_EVT_CloudPublishingMDS_Wrapper | W98: CloudMDSEquityPriceSilver.json
A99: 67 | B99: 66 | C99: Chain | E99: HOOPP_PricePublishing_Equity_Schedule | F99: Price Master | G99: HOOPP_CloudPubMDS_EquityPriceGold | H99: GC | J99: Publishing | Q99: T+1 | T99: Daily(Tue-Sat) | V99: HOOPP_EVT_CloudPublishingMDS_Wrapper | W99: CloudMDSEquityPriceGold.json
A100: 69 | B100: 68 | C100: Chain | E100: HOOPP_PricePublishing_Equity_Schedule | F100: Price Master | G100: HOOPP_CloudPubMDS_HSOIPriceSilver - Vendor ID = BB HOOPP_CloudPubMDS_HSOIPriceSilver_BB | H100: GC | J100: Publishing | Q100: T+1 | T100: Daily(Tue-Sat) | V100: HOOPP_EVT_CloudPublishingMDS_Wrapper | W100: CloudMDSHOOPPSOIPriceSilver.json
...

Sheet Pricing ADITLO Simplified
A1: TimeLine | B1: Data for? | C1: Time Trigerred (EST/EDT) | D1: Time Trigerred (IST) | E1: Key Figures Loaded? | F1: Vendor | G1: File Load? | H1: Price Load | I1: Price Validation? | J1: Price Denormalization? | K1: Publishing? | L1: Request SOI | M1: Denorm SOI | N1: Validation SOI | O1: Creation of SOI | P1: HOOPP Comment
A2: T | B2: T | C2: 0.70833333 | D2: =C2+Summary!$C$30/24 -> 1.1041667 | E2: No | F2: FX | G2: Yes | H2: Yes | I2: Yes | J2: Yes | K2: Yes | L2: FX_SOI | M2: FX_SOI | N2: FX_SOI | O2: FX_SOI: Manual One Time
A3: T | B3: T | C3: 0.75 | D3: =C3+Summary!$C$30/24 -> 1.1458333 | E3: Yes | F3: FTSE | G3: Yes | H3: Yes | I3: No | J3: No | K3: No | O3: FTSE_SOI
A4: T | B4: T-1 | C4: 0.75 | D4: =C4+Summary!$C$30/24 -> 1.1458333 | E4: No | F4: SCD | G4: Yes | H4: No | O4: OTCSOI
A5: T | B5: T | C5: 0.8125 | D5: =C5+Summary!$C$30/24 -> 1.2083333 | E5: No | F5: SVC | G5: Yes | H5: Yes | I5: No | J5: No | K5: No | L5: All Bonds from HOOPP SOI
A6: T | B6: T | C6: 0.82291667 | D6: =C6+Summary!$C$30/24 -> 1.21875 | F6: SVC/FTSE | G6: No | I6: Yes | J6: Yes | K6: Yes | M6: FTSE_SOI, EOD_BONDS | N6: EOD_BONDS
A7: T | B7: T | C7: 0.95833333 | D7: =C7+Summary!$C$30/24 -> 1.3541667 | E7: No | F7: SCD | G7: Yes | H7: No | I7: No | J7: No | K7: No | O7: HOOPP SOI(Superset), EOD_BONDS(Some Bonds from HOOP SOI), EOD_EQ(Some Equities from Hoop SOI)
A8: T+1 | B8: T-1 | C8: 0.027777778 | D8: =C8+Summary!$C$30/24 -> 0.42361111 | E8: Yes | F8: BB | G8: Yes | H8: yes | I8: Yes | J8: Yes | K8: Yes | L8: HOOP_SOI | M8: HOOPP SOI,REFRATE_SOI,FTSE_SOI,GENERIC_TICKERS_SOI | N8: EOD_EQ
A9: T | B9: T | C9: 0.84722222 | E9: Yes | F9: Markit OTC (Cred) | G9: Yes | H9: Yes | I9: No | J9: Yes | K9: Yes | M9: MarkitSOI_CDX_TRANCHE | N9: MarkitSOI_CDX_TRANCHE | P9: Depends on 38
A10: T | B10: T | C10: 0.85416667 | E10: Yes | F10: ICE | G10: Yes | H10: Yes | I10: Yes | J10: Yes | K10: Yes | M10: MarkitSOI_CC_CDS | N10: MarkitSOI_CC_CDS | P10: Depends on 36
A11: T | B11: T | C11: 0.9375 | E11: Yes | F11: ICE | G11: Yes | H11: Yes | I11: No | J11: Yes | K11: Yes | M11: ICE_SOI | P11: Depends on 36 Key Figures & Pricing published for all ICE securities?
A12: T | B12: T | C12: 0.9375 | E12: Yes | F12: Markit OTC | G12: Yes | H12: Yes | I12: No | J12: Yes | K12: Yes | M12: MarkitSOI_CDX_CDS | N12: MarkitSOI_CDX_CDS | P12: Not needed - no files impacting CDX_CDS loaded at this time
A13: T+1 | B13: T-1 | C13: 0.0625 | E13: Yes | F13: Markit OTC (SG_DAILY) | G13: Yes | H13: Yes | I13: Yes | J13: Yes | K13: Yes | M13: MarkitSOI_CDX_TRANCHE | N13: MarkitSOI_CDX_TRANCHE | P13: Depends on 35.1 | Q13: Updated Time Triggered Until and Business SLO on main tab
A14: T+1 | B14: T-1 | C14: 0.0625 | E14: Yes | F14: Markit OTC (SG_DAILY_2) | G14: Yes | H14: Yes | I14: Yes | J14: Yes | K14: Yes | M14: MarkitSOI_ABX | N14: MarkitSOI_ABX | P14: Depends on 35.2
A15: T+1 | B15: T-1 | C15: 0.0625 | E15: Yes | F15: Markit OTC (SG_DAILY) | G15: Yes | H15: Yes | I15: Yes | J15: Yes | K15: Yes | M15: MarkitSOI_BESPOKE | N15: MarkitSOI_BESPOKE | P15: Depends on 35.1
A16: T+1 | B16: T-1 | C16: 0.0625 | E16: Yes | F16: Markit OTC (SG_DAILY_2) | G16: Yes | H16: Yes | I16: Yes | J16: Yes | K16: Yes | M16: MarkitSOI_CDX_OPT | N16: MarkitSOI_CDX_OPT | P16: Depends on 35.2
A17: T+1 | B17: T-1 | C17: 0.0625 | E17: Yes | F17: Markit OTC (SG_DAILY_2) | G17: Yes | H17: Yes | I17: No | J17: Yes | K17: Yes | M17: MarkitSOI_CC_CDX_CDS | P17: Depends on 35.2
A18: T+1 | B18: T-1 | C18: 0.0625 | E18: Yes | F18: Markit OTC (SG_DAILY_2) | G18: Yes | H18: Yes | I18: No | J18: Yes | K18: Yes | M18: MarkitSOI_CDX_CDS | P18: Depends on 35.2
A19: T+1 | B19: T-1 | C19: 0.10416667 | D19: =C19+Summary!$C$30/24 -> 0.5 | E19: Yes | F19: Markit (Credit Index Pricing) | G19: Yes | H19: Yes | I19: No | J19: Yes | K19: Yes | P19: Depends on 10; mentioned as part of row 10.1 in the main ADITLO tab Key Figures & Pricing published for all Markit Credit Index securities.
A20: T+1 | B20: T-1 | C20: 0.10416667 | E20: Yes | F20: Markit CI/CDS | G20: Yes | H20: Yes | I20: Yes | J20: Yes | K20: Yes | M20: MarkitSOI_CC_CDX_CDS | N20: MarkitSOI_CC_CDX_CDS | P20: Depends on 36 & 10; however, if 10 is very late, can CC_CDX_CDS price validation run anyway at 3:30 am?
A21: T+1 | B21: T-1 | C21: 0.10416667 | E21: Yes | F21: Markit CI/CDS | G21: Yes | H21: Yes | I21: Yes | J21: Yes | K21: Yes | M21: MarkitSOI_CDX_CDS | N21: MarkitSOI_CDX_CDS | P21: Depends on 10
A22: T+1 | B22: T-1 | C22: 0.10416667 | D22: =C22+Summary!$C$30/24 -> 0.5 | E22: Yes | F22: Markit (Composite CDS) | G22: Yes | H22: Yes | I22: No | J22: Yes | K22: Yes | P22: Added as row 11.1 on ADITLO Key Figures & Pricing published for all Markit Spread securities.
A23: T | B23: T | C23: 0.47916667 | F23: World Markets | G23: Yes | H23: Yes | I23: No | J23: Yes | K23: Yes | M23: FX_WM_SOI
A24: T | B24: T | C24: 0.9375 | F24: Northern Trust | G24: Yes | H24: Yes | I24: No | J24: Yes | K24: Yes | M24: NTFX_SOI
A25: T | B25: T | C25: 0.89583333 | F25: LCH | G25: Yes | H25: Yes | I25: Yes | J25: Yes | K25: Yes | M25: LCH_SOI | N25: LCH_SOI

Sheet Legends
C2: ADITLO | D2: A Day In The Life Of "Customer" | G2: Note: 1) NO business Jobs will run on Weekends. 2) Some ADHOC jobs are necessary for NPORT data reporting and need to be manually trigerred when the file arrives on the FTP. JNAM will inform via email about file upload. 3) JNAM always provides files to load on the FTP. They notify on emails.
C3: SM | D3: Security Master
C4: DWH | D4: Data Warehouse
C5: CST/CDT | D5: Central Standard Time/Central Daylight Time
C6: EST/EDT | D6: Eastern Standard Time/Eastern Daylight Time
C7: IST | D7: Indian Standard Time
C8: AS | D8: Application Server
C9: SLA | D9: Service Level Agreement
C10: SLO | D10: Service Level Objectives
C11: SLI | D11: Service Level Indicators
C13: Header of ADITLO worksheet - description
C15: Job # | D15: task number in the order of execution on a business day
C16: Depends Job # | D16: dependednt task number in the order of execution if Chains used
C17: Job Chain Name | D17: name of the job chain in the job scheduler
C18: Task Name in Job Scheduler | D18: name used to identify the task in the Job Scheduler list of jobs for JNAM
C19: Schema | D19: schema used to process or publish the inbound/outbound files respectively.
C20: Task Type | D20: type of task - file load, publishing, alerts or miscellaneous
C21: Job Category | D21: type of job - standalone or job chain in the job scheduler
C22: Input or Output File Names | D22: name of the inbound or outbound file(s)
C23: Time Trigerred (CST/CDT) | D23: time of execution in CST or CDT
C24: Time Trigerred (EST/EDT) | D24: time of execution in EST or EDT
C25: Time Trigerred (IST) | D25: time of execution in IST
C26: Frequency | D26: frequency of job executions - daily, monthly etc
... C37: Alert Send To | D37: audience for the alert

Sheet Calendar Data
A1: CAD1STOCKMARKET | G1: US1STOCKMARKET | N1: MARKIT_HOLIDAY | Q1: MARKIT_HOLIDAYPLUS1 | T1: SVC_HOLIDAY | U1: (US & CAD Holidays) | W1: WM_HOLIDAY
A2: EventYear | B2: EventDate | C2: EventDayOfWeek | D2: EventName | G2: EventYear | H2: EventDate | I2: EventDayOfWeek | J2: EventName | N2: EventYear | O2: EventDate | Q2: EventYear | R2: EventDate | T2: EventYear | U2: EventDate | W2: EventYear | X2: EventDate
A3: 2024 | B3: 20240101 | C3: Mon | D3: New Year's Day | G3: 2024 | H3: 20240101 | I3: Mon | J3: New Year's Day | N3: 2024 | O3: 20240101 | Q3: 2024 | R3: 20240102 | T3: 2025 | U3: 20250101 | W3: 2025 | X3: 20250101
A4: 2024 | B4: 20240219 | C4: Mon | D4: Family Day | G4: 2024 | H4: 20240115 | I4: Mon | J4: Martin Luther King Jr. Day | N4: 2024 | O4: 20241225 | Q4: 2024 | R4: 20241226 | T4: 2025 | U4: 20250217 | W4: 2025 | X4: 20250418
A5: 2024 | B5: 20240329 | C5: Fri | D5: Good Friday | G5: 2024 | H5: 20240219 | I5: Mon | J5: Presidents' Day | N5: 2025 | O5: 20250101 | Q5: 2025 | R5: 20250102 | T5: 2025 | U5: 20250418 | W5: 2025 | X5: 20251225
A6: 2024 | B6: 20240520 | C6: Mon | D6: Victoria/Patriots' Day | G6: 2024 | H6: 20240329 | I6: Fri | J6: Good Friday | N6: 2025 | O6: 20251225 | Q6: 2025 | R6: 20251226 | T6: 2025 | U6: 20250901 | W6: 2026 | X6: 20260101
A7: 2024 | B7: 20240701 | C7: Mon | D7: Canada Day | G7: 2024 | H7: 20240527 | I7: Mon | J7: Memorial Day | T7: 2025 | U7: 20251225 | W7: 2026 | X7: 20260403
A8: 2024 | B8: 20240805 | C8: Mon | D8: Civic Holiday | G8: 2024 | H8: 20240619 | I8: Wed | J8: Juneteenth National Independence Day | N8: ICE_LCH_HOLIDAY | T8: 2026 | U8: 20260101 | W8: 2026 | X8: 20261225
A9: 2024 | B9: 20240902 | C9: Mon | D9: Labour Day | G9: 2024 | H9: 20240704 | I9: Thu | J9: Independence Day | N9: 2025 | O9: 20250101 | T9: 2026 | U9: 20260216
A10: 2024 | B10: 20241014 | C10: Mon | D10: Thanksgiving | G10: 2024 | H10: 20240902 | I10: Mon | J10: Labor Day | T10: 2026 | U10: 20260403
A11: 2024 | B11: 20241225 | C11: Wed | D11: Christmas | G11: 2024 | H11: 20241014 | I11: Mon | J11: Columbus Day | N11: SNP_QUARTERLY_CAL | T11: 2026 | U11: 20260907
A12: 2024 | B12: 20241226 | C12: Thu | D12: Boxing Day | G12: 2024 | H12: 20241111 | I12: Mon | J12: Veterans' Day | N12: 2025 | O12: 20250105 | T12: 2026 | U12: 20261225
A13: 2025 | B13: 20250101 | C13: Wed | D13: New Year's Day | G13: 2024 | H13: 20241128 | I13: Thu | J13: Thanksgiving | N13: 2025 | O13: 20250406
A14: 2025 | B14: 20250217 | C14: Mon | D14: Family Day | G14: 2024 | H14: 20241225 | I14: Wed | J14: Christmas | N14: 2025 | O14: 20250706
A15: 2025 | B15: 20250418 | C15: Fri | D15: Good Friday | G15: 2025 | H15: 20250101 | I15: Wed | J15: New Year's Day | N15: 2025 | O15: 20251006
A16: 2025 | B16: 20250519 | C16: Mon | D16: Victoria/Patriots' Day | G16: 2025 | H16: 20250120 | I16: Mon | J16: Martin Luther King Jr. Day
A17: 2025 | B17: 20250701 | C17: Tue | D17: Canada Day | G17: 2025 | H17: 20250217 | I17: Mon | J17: Presidents' Day
A18: 2025 | B18: 20250804 | C18: Mon | D18: Civic Holiday | G18: 2025 | H18: 20250418 | I18: Fri | J18: Good Friday
A19: 2025 | B19: 20250901 | C19: Mon | D19: Labour Day | G19: 2025 | H19: 20250526 | I19: Mon | J19: Memorial Day
A20: 2025 | B20: 20251013 | C20: Mon | D20: Thanksgiving | G20: 2025 | H20: 20250619 | I20: Thu | J20: Juneteenth National Independence Day
A21: 2025 | B21: 20251225 | C21: Thu | D21: Christmas | G21: 2025 | H21: 20250704 | I21: Fri | J21: Independence Day
A22: 2025 | B22: 20251226 | C22: Fri | D22: Boxing Day | G22: 2025 | H22: 20250901 | I22: Mon | J22: Labor Day
G23: 2025 | H23: 20251127 | I23: Thu | J23: Thanksgiving
A24: CAD2BANKHOLIDAY | G24: 2025 | H24: 20251225 | I24: Thu | J24: Christmas
A25: EventYear | B25: EventDate | C25: EventDayOfWeek | D25: EventName
A26: 2024 | B26: 20240101 | C26: Mon | D26: New Year's Day
A27: 2024 | B27: 20240219 | C27: Mon | D27: Family Day
A28: 2024 | B28: 20240329 | C28: Fri | D28: Good Friday
A29: 2024 | B29: 20240520 | C29: Mon | D29: Victoria/Patriots' Day
A30: 2024 | B30: 20240701 | C30: Mon | D30: Canada Day
A31: 2024 | B31: 20240805 | C31: Mon | D31: Civic Holiday
A32: 2024 | B32: 20240902 | C32: Mon | D32: Labour Day
A33: 2024 | B33: 20240930 | C33: Mon | D33: National Truth and Reconciliation Day
A34: 2024 | B34: 20241014 | C34: Mon | D34: Thanksgiving
A35: 2024 | B35: 20241111 | C35: Mon | D35: Remembrance Day
A36: 2024 | B36: 20241225 | C36: Wed | D36: Christmas
A37: 2024 | B37: 20241226 | C37: Thu | D37: Boxing Day
... A49: 2025 | B49: 20251226 | C49: Fri | D49: Boxing Day

Sheet Custom Pipelines
A1: Pipeline Name | B1: S3 Folder | C1: File Type | D1: Table Name | E1: Event Enabled
A2: FTSE IDXSummary DBI | B2: s3://gs-hp-us-east-1-uat-snowflake/raw_vendor_files/ftse/idxsummary_dbi/ | C2: CSV | D2: STRUCTURED.FTSE_IDXSUMMARY_DBI | E2: TRUE
A3: FTSE IDXSummary RRBI | B3: s3://gs-hp-us-east-1-uat-snowflake/raw_vendor_files/ftse/idxsummary_rrbi/ | C3: CSV | D3: STRUCTURED.FTSE_IDXSUMMARY_RRBI | E3: TRUE
A4: FTSE IDXDetails DBI UO | B4: s3://gs-hp-us-east-1-uat-snowflake/raw_vendor_files/ftse/idxdetail_dbi_uo/ | C4: CSV | D4: STRUCTURED.FTSE_IDXDETAILS_DBI_UO | E4: TRUE
A5: FTSE IDXDetails RRBI TR | B5: s3://gs-hp-us-east-1-uat-snowflake/raw_vendor_files/ftse/idxdetail_rrbi_tr/ | C5: CSV | D5: STRUCTURED.FTSE_IDXDETAILS_RRBI_TR | E5: TRUE
A6: FTSE IDXDetails RRBI UO | B6: s3://gs-hp-us-east-1-uat-snowflake/raw_vendor_files/ftse/idxdetail_rrbi_uo/ | C6: CSV | D6: STRUCTURED.FTSE_IDXDETAILS_RRBI_UO | E6: TRUE
A7: FTSE IDXDetails DBI TR | B7: s3://gs-hp-us-east-1-uat-snowflake/raw_vendor_files/ftse/idxdetail_dbi_tr/ | C7: CSV | D7: STRUCTURED.FTSE_IDXDETAILS_DBI_TR | E7: TRUE
A8: FTSE SCMMKT | B8: s3://gs-hp-us-east-1-uat-snowflake/raw_vendor_files/ftse/scmmkt/ | C8: CSV | D8: STRUCTURED.FTSE_SCMMKT | E8: TRUE
A9: Bloomberg | B9: s3://gs-hp-us-east-1-uat-snowflake/raw_vendor_files/bb_per_sec/ | C9: BLOOMBERG | D9: STRUCTURED.BLOOMBERG | E9: TRUE
A10: SCD | B10: s3://gs-hp-us-east-1-uat-snowflake/raw_vendor_files/scd/ | C10: CSV | D10: STRUCTURED.SCD | E10: TRUE
A11: SnP Ratings | B11: s3://gs-hp-us-east-1-uat-snowflake/raw_vendor_files/snp_ratings/ | C11: S&P | D11: STRUCTURED.SNP_RATINGS | E11: TRUE
A12: Moodys Instrument Ratings | B12: s3://gs-hp-us-east-1-uat-snowflake/raw_vendor_files/moodys/instruments_ratings/ | C12: MOODYS: Ratings | D12: STRUCTURED.MOODYS_INSTRUMENT_RATINGS | E12: TRUE
A13: Moodys Organization Ratings | B13: s3://gs-hp-us-east-1-uat-snowflake/raw_vendor_files/moodys/organization_ratings/ | C13: MOODYS: Ratings | D13: STRUCTURED.MOODYS_ORGANIZATION_RATINGS | E13: TRUE
... A35: LCH Trade Prices | B35: s3://gs-hp-us-east-1-uat-snowflake/raw_vendor_files/lch/ | C35: S&P: Index | D35: STRUCTURED.LCH_TRADE_PRICES_FEED | E35: TRUE
A36: HOOPP NT Security Master CSM | B36: s3://gs-hp-us-east-1-uat-snowflake/raw_vendor_files/northerntrust/security_master_csm | C36: CSV | D36: STRUCTURED.HOOPP_NT_DAILY_SECURITY_MASTER_CSM_FEED
A37: HOOPP NT Daily Positions CSM | B37: s3://gs-hp-us-east-1-uat-snowflake/raw_vendor_files/northerntrust/daily_positions_csm | C37: CSV | D37: STRUCTURED.HOOPP_NT_DAILY_POSITIONS_CSM_FEED | E37: TRUE
A38: HOOPP NT FMH2956S GSL Lending Report | B38: s3://gs-hp-us-east-1-uat-snowflake/raw_vendor_files/northerntrust/fmh2956s_gsl_lending_report | C38: CSV | D38: STRUCTURED.HOOPP_NT_FMH2956S_GSL_LENDING_REPORT_FEED | E38: TRUE
A39: HOOPP NT Daily Transactions | B39: s3://gs-hp-us-east-1-uat-snowflake/raw_vendor_files/northerntrust/daily_transactions_csm | C39: CSV | D39: STRUCTURED.HOOPP_NT_DAILY_TRANSACTIONS_CSM_FEED | E39: TRUE
A40: HOOPP NT Daily Collateral SRD2904 CSM | B40: s3://gs-hp-us-east-1-uat-snowflake/raw_vendor_files/northerntrust/daily_collaterial_srd2904_csm | C40: CSV | D40: STRUCTURED.HOOPP_NT_DAILY_COLLATERIAL_SRD2904_CSM_FEED | E40: TRUE | F40: aws s3 ls s3://gs-hp-us-east-1-prod-snowflake/gs_hoopp_files/nt/2025/11/06/
A41: HOOPP NT Monthly Positions CSM | B41: s3://gs-hp-us-east-1-uat-snowflake/raw_vendor_files/northerntrust/monthly_position_csm | C41: CSV | D41: STRUCTURED.HOOPP_NT_MONTHLY_POSITIONS_CSM_FEED | E41: TRUE
A42: HOOPP WMR Spots | B42: s3://gs-hp-us-east-1-uat-snowflake/raw_vendor_files/wmr/wmr_spots | C42: CSV | D42: STRUCTURED.HOOPP_WMR_SPOTS_FEED | E42: TRUE
A43: HOOPP WMR Forwards Outright | B43: s3://gs-hp-us-east-1-uat-snowflake/raw_vendor_files/wmr/wmr_fwds_outright | C43: CSV | D43: STRUCTURED.HOOPP_WMR_FORWARDS_OUTRIGHT_FEED | E43: TRUE
A44: HOOPP Broker CIBC Fee | B44: s3://gs-hp-us-east-1-uat-snowflake/raw_vendor_files/broker_files/cibc/fee | C44: CSV | D44: STRUCTURED.HOOPP_BROKER_CIBC_FEE_FEED | E44: TRUE
A45: HOOPP Broker CIBCWM Fee | B45: s3://gs-hp-us-east-1-uat-snowflake/raw_vendor_files/broker_files/cibcwm/fee | C45: CSV | D45: STRUCTURED.HOOPP_BROKER_CIBCWM_FEE_FEED | E45: TRUE
A46: HOOPP Broker SCM Fee | B46: s3://gs-hp-us-east-1-uat-snowflake/raw_vendor_files/broker_files/scm/fee | C46: CSV | D46: STRUCTURED.HOOPP_BROKER_SCM_FEE_FEED | E46: TRUE
A47: HOOPP Broker GS Positions | B47: s3://gs-hp-us-east-1-uat-snowflake/raw_vendor_files/broker_files/gs/positions | C47: CSV | D47: STRUCTURED.HOOPP_BROKER_GS_POSITIONS_FEED | E47: TRUE
A48: HOOPP Broker NATIXIS Positions | B48: s3://gs-hp-us-east-1-uat-snowflake/raw_vendor_files/broker_files/natixis/positions | C48: CSV | D48: STRUCTURED.HOOPP_BROKER_NATIXIS_POSITIONS_FEED | E48: TRUE
A49: HOOPP Broker NT Positions | B49: s3://gs-hp-us-east-1-uat-snowflake/raw_vendor_files/broker_files/nt/positions | C49: CSV | D49: STRUCTURED.HOOPP_BROKER_NT_POSITIONS_FEED | E49: TRUE
A50: HOOPP Broker BMO Positions | B50: s3://gs-hp-us-east-1-uat-snowflake/raw_vendor_files/broker_files/bmo/positions | C50: CSV | D50: STRUCTURED.HOOPP_BROKER_BMO_POSITIONS_FEED | E50: TRUE
A51: HOOPP Broker CIBCWM Positions | B51: s3://gs-hp-us-east-1-uat-snowflake/raw_vendor_files/broker_files/cibcwm/positions | C51: CSV | D51: STRUCTURED.HOOPP_BROKER_CIBCWM_POSITIONS_FEED | E51: TRUE
A52: HOOPP Broker TDSI Positions | B52: s3://gs-hp-us-east-1-uat-snowflake/raw_vendor_files/broker_files/tdsi/positions | C52: CSV | D52: STRUCTURED.HOOPP_BROKER_TDSI_POSITIONS_FEED | E52: TRUE
... A59: HOOPP Broker NATLBK Positions | B59: s3://gs-hp-us-east-1-uat-snowflake/raw_vendor_files/broker_files/natlbk/positions | C59: CSV | D59: STRUCTURED.HOOPP_BROKER_NATLBK_POSITIONS_FEED | E59: TRUE

Sheet Vendor Connections
A1: Vendor License Category | B1: Vendor File Names | C1: OOB/Custom | D1: Release | E1: GS Connection Type | F1: Hoop ConnectionType | G1: File Name Pattern | H1: File Format | I1: Folder | J1: URL | K1: Port | L1: Username | M1: Password | N1: Status | O1: Additional Notes | P1: Third Party Agreemetn required ? | Q1: Parallel Download Allowed? | S1: Time
A2: Bloomberg
A3: Bloomberg DL Per Security | B3: gs00000*.res | C3: OOB | D3: 1 | E3: SFTP(RR) | F3: SFTP | G3: gs0000*.out | I3: / | J3: dlsftp.bloomberg.com | K3: 30206 | L3: dl202842 | N3: Active | O3: Current MFT jobs file pattern: Download: PDI*.csv, PDI*.err Upload: PDI*.req | P3: Complete | R3: BBG required GS Whitelist of IP and SSH Keys
A4: Bloomberg DL Bulk(Back Office) | C4: OOB | D4: Hana Phase | E4: SFTP(Bulk Download) | F4: SFTP | G4: shareFuturesAsia?.out.gz.YYYYMMDD shareFuturesAsia?.px.gz.YYYYMMDD shareFuturesEuro.out.gz.YYYYMMDD shareFuturesEuro.px.gz.YYYYMMDD shareFuturesNamr.out.gz.YYYYMMDD shareFuturesNamr.px.gz.YYYYMMDD shareFuturesLamr.out.gz.YYYYMMDD shareFuturesLamr.px.gz.YYYYMMDD | I4: / | J4: dlsftp.bloomberg.com | K4: 30206 | L4: dl789909 | N4: Active | O4: Required for Dividend Futures FIle | P4: Complete | R4: BBG required GS Whitelist of IP and SSH Keys
A5: Bloomberg DL Bulk(Back Office) | C5: OOB | D5: 1 | E5: SFTP(Bulk Download) | F5: SFTP | I5: / | J5: dlsftp.bloomberg.com | K5: 30206 | L5: dl789909 | N5: Active | O5: Required for Corporate Structure | P5: Complete | R5: BBG required GS Whitelist of IP and SSH Keys
A6: Simcorp
A7: Simcorp SMF | B7: SCD_SMF*.csv | C7: Custom | D7: 1 | E7: SFTP | P7: Not Required - Internal | S7: 6:15 PM , 9:05 PM , 4-6 AM
A8: Markit (RED)
A9: Markit Indices | B9: CDS_COMPOSITE_BY_CONVENTION.zip | C9: OOB | D9: 2 | E9: to be added later
A10: Markit Indices | B10: INDEX_COMPOSITE_CDX.zip | C10: OOB | D10: 2 | E10: HTTP
A11: Markit Indices | B11: INDEX_COMPOSITE_ITRAXX-EUROPE.zip | C11: OOB | D11: 2 | E11: HTTP
A12: Markit RED | B12: RED_ENTITY.zip | C12: OOB | D12: 2 | E12: HTTP | F12: SFTP | G12: RED_ENTITY-YYYYMMDD.zip | I12: /CDS | J12: sftp2.ihsmarkit.com | K12: 22 | L12: Corporate User: HOOPP | M12: Corporate Pass: hNFB@4HA | N12: Active | O12: Confirm update to corporate account versus user named | P12: Complete
A13: Markit RED | B13: RED_OBLIGATION.zip | C13: OOB | D13: 2 | E13: HTTP | F13: SFTP | G13: RED_OBLIGATION-YYYYMMDD.zip | I13: /CDS | J13: sftp2.ihsmarkit.com | K13: 22 | L13: Corporate User: HOOPP | M13: Corporate Pass: hNFB@4HA | N13: Active | O13: Confirm update to corporate account versus user named | P13: Complete
A14: Markit RED | B14: RED_CDX_DYNAMIC.zip | C14: OOB | D14: 2 | E14: HTTP | F14: SFTP | G14: RED_CDX_DYNAMIC-YYYYMMDD.zip | I14: /CDS | J14: sftp2.ihsmarkit.com | K14: 22 | L14: Corporate User: HOOPP | M14: Corporate Pass: hNFB@4HA | N14: Active | O14: Confirm update to corporate account versus user named | P14: Complete
A15: Markit CDS Pricing | B15: RED_ITRAXX_EUR_DYNAMIC.zip | C15: OOB | D15: 2 | E15: to be added later | F15: SFTP | G15: RED_ITRAXX_EUR_DYNAMIC-YYYYMMDD.zip | I15: /CDS | J15: sftp2.ihsmarkit.com | K15: 22 | L15: Corporate User: HOOPP | M15: Corporate Pass: hNFB@4HA
A16: Markit CDS Pricing | B16: HOOPP_SG_DAILY_2.xml | C16: OOB | D16: 2 | E16: SFTP | F16: SFTP | G16: HOOPP_SG_DAILY_2.DDMonYY.csv | I16: /HOOPP_SG_DAILY_2/PV/Results | J16: files-eu.ihsmarkit.com | K16: 22 | L16: HOOPP_PV@hoopp.com | M16: hxx3Eizu
A17: Markit CDS Pricing | B17: HOOPP_SG_DAILY_CRED.xml | C17: OOB | D17: 2 | E17: SFTP | F17: SFTP | G17: HOOPP_SG_DAILY_CRED.DDMonYY.csv | I17: /HOOPP_SG_DAILY_CRED/PV/Results | J17: files-eu.ihsmarkit.com | K17: 22 | L17: HOOPP_PV@hoopp.com | M17: hxx3Eizu
A18: Markit CDS Pricing | B18: HOOPP_SG_DAILY.xml | C18: OOB | D18: 2 | E18: SFTP | F18: SFTP | G18: HOOPP_SG_DAILY.DDMonYY.csv | I18: /HOOPP_SG_DAILY/PV/Results | J18: files-eu.ihsmarkit.com | K18: 22 | L18: HOOPP_PV@hoopp.com | M18: hxx3Eizu
A19: Markit CDS Pricing 2025 | G19: same file name patterns as before | I19: same folder structures as before | J19: sftp1.spglobal.com | K19: 22 | L19: HOOPP_PV@hoopp.com | M19: hxx3Eizu$2025
A20: Markit MCA 15022 | B20: mca_prop_c# (5 cycles) MARKIT_CORP_ACTIONS_EVENT_INFO MARKIT_CORP_ACTIONS_OPTION_INFO MARKIT_CORP_ACTIONS_PAYOUT_INFO MARKIT_CORP_ACTIONS_TEXT_INFO | C20: OOB | D20: HANA | E20: HTTP
A21: SVC
A22: Main Price File | B22: SCD_SVC_PRICE_YYMMDD.txt | C22: Custom | D22: 1 | F22: SFTP | G22: SCD_SVC_PRICE_YYMMDD.txt | I22: / | J22: ftp.svco.com | K22: 22 | L22: SVCZ106 | M22: nUye2DBE | O22: discuss PROD approach with GS | P22: Not Required
B23: SCD_SVC_UNMATCHED_YYMMDD.txt | C23: Custom | D23: 1 | F23: SFTP | G23: SCD_SVC_UNMATCHED_YYMMDD.txt | I23: / | J23: ftp.svco.com | K23: 22 | L23: SVCZ106 | O23: discuss PROD approach with GS | P23: Not Required
B24: SCD_SVC_PRT_YYMMDD.txt | C24: Custom | D24: 1 | F24: SFTP | G24: SCD_SVC_PRT_YYMMDD.txt | I24: / | J24: ftp.svco.com | K24: 22 | L24: SVCZ106 | O24: discuss PROD approach with GS | P24: Not Required
B25: SCD_SVC_INACTIVE_YYMMDD.txt | C25: Custom | D25: 1 | F25: SFTP | G25: SCD_SVC_INACTIVE_YYMMDD.txt | I25: / | J25: ftp.svco.com | K25: 22 | L25: SVCZ106 | O25: discuss PROD approach with GS | P25: Not Required
B26: SCD_SVC_STALE_YYMMDD.txt | C26: Custom | D26: 1 | F26: SFTP | G26: SCD_SVC_STALE_YYMMDD.txt | I26: / | J26: ftp.svco.com | K26: 22 | L26: SVCZ106 | O26: discuss PROD approach with GS | P26: Not Required
A27: FTSE
A28: DBI Index | B28: idxsummary_dbi.csv | C28: Custom | D28: 1 | F28: SFTP | G28: idxsummary_dbi.csv | I28: /data/PCBond/scindex | J28: data.ftse.com | K28: 22 | L28: FQHOOPP | M28: e`P{i~#lMP | O28: discuss PROD approach with GS | P28: Not Required
A29: RRBI Index | B29: idxsummary_rrbi.csv | C29: Custom | D29: 1 | F29: SFTP | G29: idxsummary_rrbi.csv | I29: /data/PCBond/rrbi | J29: data.ftse.com | K29: 22 | L29: FQHOOPP | O29: discuss PROD approach with GS | P29: Not Required
A30: Money Market Index | B30: scmmkt.csv | C30: Custom | D30: 1 | F30: SFTP | G30: scmmkt.csv | I30: /data/PCBond/scmmkt | J30: data.ftse.com | K30: 22 | L30: FQHOOPP | O30: discuss PROD approach with GS | P30: Not Required
A31: DBI Constituents Return Level data | B31: idxdetail_dbi_tr.csv | C31: Custom | D31: 1 | F31: SFTP | G31: idxdetail_dbi_tr.csv | I31: /data/PCBond/deidxtr | J31: data.ftse.com | K31: 22 | L31: FQHOOPP | O31: discuss PROD approach with GS | P31: Not Required
A32: DBI Constituents Risk Level data | B32: idxdetail_dbi_uo.csv | C32: Custom | D32: 1 | F32: SFTP | G32: idxdetail_dbi_uo.csv | I32: /data/PCBond/deindex | J32: data.ftse.com | K32: 22 | L32: FQHOOPP | O32: discuss PROD approach with GS | P32: Not Required
A33: RRBI Constituents Return Level data | B33: idxdetail_rrbi_tr.csv | C33: Custom | D33: 1 | F33: SFTP | G33: idxdetail_rrbi_tr.csv | I33: /data/PCBond/deidxtr | J33: data.ftse.com | K33: 22 | L33: FQHOOPP | O33: discuss PROD approach with GS | P33: Not Required
A34: RRBI Constituents Risk Level data | B34: idxdetail_rrbi_uo.csv | C34: Custom | D34: 1 | F34: SFTP | G34: idxdetail_rrbi_uo.csv | I34: /data/PCBond/DEIDXRR | J34: data.ftse.com | K34: 22 | L34: FQHOOPP | O34: discuss PROD approach with GS | P34: Not Required
A35: Copp Clark
A36: Holiday Data Service | D36: 4 | E36: SFTP | G36: FinancialCentres_20241107.csv.zip FileExchangeTrading_20241107.csv.zip FileExchangeSettlement_20241107.csv.zip FileCurrencies_20241107.csv.zip | I36: /hoopp.hds | J36: sftp.coppclark.com | K36: 22 | L36: hoopp.hds | M36: Nr1~)^=5 | O36: limit connections to the server no more than once every 30 minutes
A37: S&P Xpressfeed Ratings
A38: Xpress ratings | B38: RTG_SP_ | C38: OOB | D38: 1 | E38: SFTP | F38: SFTP | J38: edx.spglobal.com | K38: 22 | L38: Hosp0736 | M38: 5a4f4hnC | O38: discuss PROD approach with GS | P38: Not Required | R38: Confirm main and delta, issue and issuer ratings | S38: 0.625 | T38: Daily | U38: \Products\
A39: Index | B39: SP500 | C39: OOB | D39: 2 | E39: to be added later | F39: SFTP | G39: YYYYMMDD_SP500_CLS.SDC | I39: /Products/SP_US_EOD | J39: edx.standardandpoors.com | K39: 22 | L39: hooppim | M39: Trn4bt0 | O39: In discussion with Volker and S&P | P39: TBD
A40: Constituents | B40: SP500_CLS | C40: OOB | D40: 2 | E40: to be added later | F40: SFTP | G40: YYYYMMDD_SP500.SDL | I40: /Products/SP_US_EOD | J40: edx.standardandpoors.com | K40: 22 | L40: hooppim | M40: Trn4bt0 | O40: In discussion with Volker and S&P | P40: TBD
A41: Index (350+ files) | B41: If needed, can provide full list | E41: to be added later | R41: Why are these not loaded?
A42: Moodys Analytics
A43: Ratings | F43: SFTP | J43: Transfer.Moodys.com | K43: 22 | L43: InvestmentAllocations_RDS | M43: v7R9E6m5 | O43: In discussion with Volker and S&P | P43: TBD
A44: TSX
A45: Index | B45: SPTSX_PACKAGE_2_CLS_SDC.zip (20 extracts) | C45: OOB | D45: 2 | E45: to be added later | F45: SFTP | G45: YYYYMMDD_SPTSX_PACKAGE_2_CLS_SDC.zip | I45: / | J45: sftp.tmxwebstore.com | K45: 2222 | L45: A-team@hoopp.com | M45: Tb394xgp7 | O45: In discussion with Volker and S&P
A46: Constituents | B46: SPTSX_INDEX_SDL.zip (57 extracts) | C46: OOB | D46: 2 | E46: to be added later | F46: SFTP | G46: YYYYMMDD_SPTSX_INDEX_SDL.zip | I46: / | J46: sftp.tmxwebstore.com | K46: 2222 | L46: A-team@hoopp.com | M46: Tb394xgp7 | O46: In discussion with Volker and S&P
A47: Refinitive
A48: Refinitiv DataScope Select [DSS] | B48: us_treasury_prices.csv us_treasury_fi_analytics.csv | D48: HANA | E48: SFTP
A49: API/WEB service request to TR | B49: LEI_Credit_Ratings.csv | D49: HANA | E49: to be added later
A50: Generated from Data Scope | B50: Daily_Pricing_CMBS_Extract.csv HOOPP CLO.xls OnD_0x07*.csv | D50: HANA | E50: SFTP
A51: MSCI
A52: MSCI Real Estate | B52: Data_Global_Intel_CA_A00A Data_Global_Intel_LABELS Data_MNIntel_CAD_VARIABLE Data_MNIntel_LABELS | D52: HANA | E52: to be added later
A53: DBRS Morningstar
A54: LEI Ratings | B54: HOOPP4_DBPTF | D54: HANA | E54: SFTP
A55: ESMA
A56: ESMA | B56: esma | D56: HANA | E56: to be added later
A57: ESMA_FIRDS_DELTA | B57: DLTINS | D57: HANA | E57: to be added later
A58: ESMA_FIRDS_UK_DELTA | B58: UK_DLTINS | D58: HANA | E58: to be added later
A59: ESMA_SOVEREIGN_DEBT | B59: eu_debt | D59: HANA | E59: to be added later
A60: ESMA_UK | B60: uk_esma | D60: HANA | E60: to be added later
A61: ESMA_UK_SOVEREIGN_DEBT | B61: Sovereign_Debt | D61: HANA | E61: to be added later
A62: Factset
A63: Country of Risk | B63: countryfile_[YYYY][MM][DD].txt | D63: HANA | E63: to be added later
A64: MorningStar
A65: Daily / Consolidated SPBDAL | B65: SPBDAL.SPLLL SPBDALL.SPFIL | D65: HANA | E65: to be added later
A66: Daily / Weekly SPBDAL Constituents | B66: SPBDAL.SPLLC SPBDAL_Components | D66: HANA | E66: to be added later
A67: Nothern Trust
A68: FX Rates | B68: DAILY_TRANSACTIONS_SRD3363_CSM | C68: Custom | D68: 4 | F68: SFTP | G68: DAILY_TRANSACTIONS_SRD3363_CSM_20240627_201907.CSV | I68: /HOOPP1S/OUTBOUND | J68: secure-b2bi.ntrs.com | K68: 4022 | L68: HOOPP1S | M68: E74gb#Zq5TuNh | P68: Not Required
A69: Security Master | B69: SECURITY_MASTER_CSM | C69: Custom | D69: 4 | F69: SFTP | G69: SECURITY_MASTER_CSM_20240627_201904.CSV | I69: /HOOPP1S/OUTBOUND | J69: secure-b2bi.ntrs.com | K69: 4022 | L69: HOOPP1S | M69: E74gb#Zq5TuNh | P69: Not Required
A70: Security Lending | B70: ntsl__20231127.txt | C70: Custom | D70: 4 | P70: Not Required
A71: Collateral Positions | B71: DAILY_COLLATERIAL_SRD2904_CSM | C71: Custom | D71: 4 | F71: SFTP | G71: DAILY_COLLATERIAL_SRD2904_CSM_20240627_222839.CSV | I71: SFTP | J71: secure-b2bi.ntrs.com | K71: 4022 | L71: HOOPP1S | M71: E74gb#Zq5TuNh | P71: Not Required
A72: Daily / Monthly Positions | B72: DAILY_POSITIONS_CSM MONTHLY_POSITION_CSM | C72: Custom | D72: 4 | F72: SFTP | G72: DAILY_POSITIONS_CSM_20240627_201907.CSV | I72: /HOOPP1S/OUTBOUND | J72: secure-b2bi.ntrs.com | K72: 4022 | L72: HOOPP1S | M72: E74gb#Zq5TuNh | P72: Not Required
A73: Daily Transactions | B73: DAILY_TRANSACTIONS_CSM | C73: Custom | D73: 4 | F73: SFTP | G73: DAILY_TRANSACTIONS_CSM_20240627_201906.CSV | I73: /HOOPP1S/OUTBOUND | J73: secure-b2bi.ntrs.com | K73: 4022 | L73: HOOPP1S | M73: E74gb#Zq5TuNh | P73: Not Required
A74: Goldman Sachs
A75: FX Rates(Spot) | B75: intraday_fx.HOOPS | C75: Custom | D75: 4 | F75: SFTP | G75: 20240708.intraday_fx.HOOPS.csv | I75: /outgoing | J75: sfx2.gs.com | K75: 22 | L75: fut_HOOPS | M75: bBk_7834Zv
A76: CME
A77: CME cleared IRS prices | B77: IRSTR_HPP_yyyymmdd_EOD.csv | C77: Custom | D77: 3 | F77: SFTP | G77: IRSTR_HPP_20240705_EOD.csv | I77: /cme/ftp/HPP/Outgoing | J77: sftpng.cmegroup.com | K77: 22 | L77: FHPPFTP
A78: ICE
A79: CME cleared IRS prices | B79: IRSTR_HPP_yyyymmdd_EOD.csv | C79: Custom | D79: 3 | F79: SFTP | G79: IRSTR_HPP_20240705_EOD.csv | I79: /cme/ftp/HPP/Outgoing | J79: sftpng.cmegroup.com | K79: 22 | L79: FHPPFTP
A80: CDS / CDX Prices | B80: ICC_CDSSingleNameClearingEligibleInstruments ICC_hoopp_FinalEODSettlements ICC_hoopp_PositionMTMMarginDetail | C80: Custom | D80: 3 | F80: SFTP | I80: / / / | J80: mft.icelink.ice.com | K80: 22 | L80: svc-mft-ilhoopp | N80: <no Password> Connects using 4096 bit key
A81: CDS / CDX | B81: ICC_CDSIndexClearingEligibleInstruments | C81: Custom | D81: B | F81: SFTP | G81: ICC_CDSIndexClearingEligibleInstruments_20240705.csv | I81: / | J81: mft.icelink.ice.com | K81: 22 | L81: svc-mft-ilhoopp | N81: <no Password> Connects using 4096 bit key
A82: CDS Option Prices | B82: ICC_hoopp_FinalSettlements_SW2-OPT | C82: Custom | D82: 3 | F82: SFTP | G82: ICC_hoopp_FinalSettlements_20240705_SW2-OPT.csv | I82: / | J82: mft.icelink.ice.com | K82: 22 | L82: svc-mft-ilhoopp | N82: <no Password> Connects using 4096 bit key
A83: LSE
A84: Cleared Interest Rate Swaps Prices | B84: P-PSWC-HOOPPXXX_FDM-date-140439_date_REP000F1a - Trade Level Pricing_ 1.TXT | C84: Custom | D84: 3 | F84: SFTP | G84: P-PSWC-HOOPPXXX_FDM-20240705-015605_20240705_REP000F1e - Trade Level Pricing_ 1.TXT | I84: /HOOPPXXX_FDM/SwapClear/ | J84: sftp-client-clearingservices.lch.com | K84: 22 | L84: lchsftp1@hoopp.com | M84: A@X[bl44vSJt
A85: World Market (WM)
A86: FX Spot Rates | B86: wmr | C86: Custom | D86: 4 | F86: SFTP | G86: wmrDDMM.csv | I86: /data/WMR_Spots/UK-4pm-wmr/ | J86: download.wmrbenchmarks.lseg.com | K86: 22 | L86: Healthca1486 | M86: u6@o4/3m
A87: Broker Files
A88: TD | D88: 4 | F88: SFTP | G88: tdsi_hoopp_loan_fees_03 Account_07-08-2024.csv TD position file_07-08-2024.csv | I88: /user_hoopp/reports/ | J88: tdsecurities.ftptoday.com | K88: 22 | L88: user_hoopp | M88: 91user88 | O88: (Manesh) Password is up-to-date | Q88: Yes
A89: CIBC | D89: 4 | F89: SFTP | G89: cibc_hoopp_fee_20240709.csv cibc_hoopp_fee_20240709.csv | I89: /hoopp_out | J89: ssh.fh.efts.cibc.ca | K89: 22 | L89: cmt_hoopp_feed | M89: CM2Hoopp123$ | O89: (Cindy) Password is only for PROD, UAT has no password. 2048 bit SSH Key is mandatory UAT SSH PASSPHRASE: f*ZF5RE25q%* PROD SSH PASSPHRASE: f*ZF5RE25q%*1123 | Q89: No, HOOPP Collateral_*.txt, HOOPP Loands*.txt, cibc_hoopp_holdings_*.csv and cibc_hoopp_fee_*.csv deleted after download
A90: RBC | D90: 4 | F90: SFTP | G90: RBCDS_FEE_HOOPP_20240710.csv RBCDS_POS_HOOPP_20240710.txt | I90: /outbound/ | J90: sftp.rbc.com | K90: 22 | L90: YCM1UB4Y | M90: Upsuns66 | O90: (Manesh) Password is up-to-date. 1024 bit SSH Key is mandatory | Q90: Yes, archived in /archive/ZMI0/ folder
A91: RBC Dexia | F91: SFTP | G91: RBCIS_POS_HOOP_20241002.TXT | I91: /hoopp/RBCDexia | J91: sftp2.hoopp.com | K91: 22 | L91: rbc | N91: (hosted by HOOPP thru a reseller iLAP) | O91: (Cindy) No Password. 2048 bit SSH Key is mandatory | Q91: Yes, archived in /hoopp/RBCDexia/Archive
A92: Goldman Sachs | D92: 4 | F92: SFTP | G92: HOOPP Recon 2024-07-08.csv | I92: /outgoing/ | J92: sfx2.gs.com | K92: 22 | L92: hoopp_cc | M92: +mN!t#qLI[Z1GjI( | N92: NEW PASSWORD FOR HOOPP_CC PLS UPDATE | O92: (Manesh) Password is up-to-date. No SSH Key | Q92: No, HOOPP Recon 20*.csv deleted after download
A93: BMO | D93: 4 | F93: SFTP | G93: bmo_hoopp_pos_20240705.csv | I93: /Home/GEP/HOOPP/outgoing | J93: filedrop.bmocm.com | K93: 22 | L93: hooppsftp | M93: E4?APFEX6*]gv | N93: New Password updated | O93: (Manesh) Password out-of-date. New password updated in the sheet | Q93: Yes, archived to /Home/GEP/HOOPP/outgoing/Archive after 24 hours
A94: Natixis | D94: 4 | F94: FTP | G94: LoanetHooppReport_20240708.csv.gpg | I94: /natixis | J94: 216.223.152.3 | K94: 21 | L94: hooppftp1 | M94: tiMe2e5y | N94: (hosted by HOOPP thru a reseller iLAP) | O94: (Manesh) Password is up-to-date | Q94: Yes, archived to /natixis/Archive
A95: Scotia | D95: 4 | F95: SFTP | G95: HOOPPS.SCM_FEE_HOOPP_20240708.TXTHOOPPS.SCM_POS_HOOPP_20240708.TXT | I95: / | J95: pymthwy.scotiabank.com | K95: 22 | L95: HOOPPS | N95: <no Password> Connects using SSH key | O95: (Cindy) no Password. 1024 bit SSH Key is mandatory | Q95: No, HOOPPs.SCM_FEE_HOOPP*.txt and HOOPPs.SCM_POS_HOOPP_*.txt deleted after download
A96: Nothern Trust | D96: 4 | F96: SFTP | G96: FMH3676S_DAILY_GSL_POSITION_FILE_20240708.csv | I96: /HOOPP1S/OUTBOUND | J96: secure-b2bi.ntrs.com | K96: 4022 | L96: HOOPP1S | M96: E74gb#Zq5TuNh | Q96: No
A97: National Bank | F97: SFTP | G97: HOOPP_DAILY_20241126.csv | I97: /bnc | J97: sftp.hoopp.com | K97: 22 | L97: hoopp | N97: (hosted by HOOPP thru a reseller iLAP) | O97: (Cindy) no Password. 1024 bit SSH Key is mandatory | Q97: Yes, archived to /bnc/Archived
A99: Update missing Broker Connections

Sheet Version History
A1: DATE | B1: USER | C1: Modified Job Chain | D1: Modified Job | E1: Comment

Sheet Delete_Pricing_Results
A1: How we can clean ISPS and GPCS tables
A2: Sq No | B2: Step
A3: 1 | B3: Identify the group to be cleaned along with the date
A4: 2 | B4: Run this procedure by passing in the above params. This is a sample command: call delete_golden_prices_only_isps_gpcs('GV_EOD_BONDS_PD_LONG_FV','2023-10-03');

Sheet HOOPP Alerting Requirements
A2: HOOPP Alert Matrix
A4: Types of Alerts/Reports | B4: To be Actioned By | C4: Notified to | D4: Alert or Report | E4: Frequency | F4: Dev Work Required | G4: Additional Comment
A5: File movement Failure Scenario
A6: GS to vendor | B6: GS | C6: HOOPP | D6: Report | E6: Monthly | F6: TBD | G6: No immediate alert to be sent to HOOPP however should be part of Monthly Report in Files delayed or not available report. GS MS team to take care of this.
A7: Vendor to GS | B7: GS | C7: HOOPP | D7: Report | E7: Monthly | F7: TBD | G7: No immediate alert to be sent to HOOPP however should be part of Monthly Report in Files delayed or not available report. GS MS team to take care of this.
A8: Market data loads to ODS | B8: GS | C8: HOOPP | D8: Alert | E8: Immediate | F8: No | G8: An alert should be sent to HOOPP if SLO is breached
A9: ODS to S3 (Raw) | B9: GS | C9: HOOPP | D9: Alert | E9: Immediate | F9: No | G9: An alert should be sent to HOOPP if SLO for the publishing is breached.
A10: ODS to S3 (Refined) | B10: GS | C10: HOOPP | D10: Alert | E10: Immediate | F10: No | G10: An alert should be sent to HOOPP if SLO for the publishing is breached.
A11: S3 to SF (Raw Structured) | B11: TBD
A12: S3 to SF (Refined) | B12: TBD
A13: Delay in Job Completion Alert | B13: GS | C13: HOOPP | D13: Alert | E13: Immediate | F13: No | G13: If there is any Price Validation job specific SLO defined then an alert to be sent to HOOPP
A14: SF to SCD | B14: TBD Internally not in scope of soft go live
A15: SCD to ODS | B15: TBD Internally not in scope of soft go live
A16: S3 to SF | B16: TBD Internally not in scope of soft go live
A17: SCD to SF (Via HANA)
A18: Other Alerts/Reports
A19: GS Exceptions - Record count, Fails, Warnings | B19: Techincal - GS Business - HOOPP | C19: HOOPP | D19: Report | E19: Daily | F19: Yes | G19: The current dashboard allow us to view exceptions and load data for a day and there is no way to do view D-o-D comparison. . (See tab Load Error Report) Hence GS should develop a Daily Report highlighting cases where there is a difference in D-o-D exception count. The report should also have details like Average Record Count and Expected Record Count. GS also suggested that they can build exception threshold alerts.
A20: Scheduled sequence | B20: GS | C20: HOOPP | D20: Report | E20: Daily | F20: Yes | G20: Daily report showing the scheduler run status for that day including SLO Breaches, manual interventions, dependency checks. Should have red, green, and amber status of jobs for Ops team to review.
A21: SLO Breaches Report | B21: GS | C21: HOOPP | D21: Report | E21: Monthly | F21: Yes | G21: Report highlighting all the SLO breaches trends and the reason of those SLO breaches i.e. Vendor delay, GS performance Issues
A22: Files delayed or not available | B22: GS | C22: HOOPP | D22: Report | E22: Monthly | F22: Yes | G22: Monthly report - not issue to us unless delays overnight
A23: SLO Breaches | B23: GS | C23: HOOPP | D23: Alert | E23: Immediate | F23: No | G23: Any type of SLO breach should be reported to HOOPP as it occurs
A25: All the alerts which are critical for soft go live are marked in Red.
A26: All the alerts should go to goldensourceoperations@hoopp.com
A27: As of now alerting and monitoring scope is only till S3 and from S3 to SF monitoring part is still in discussion.
A28: GS MS team to chase the vendor for any file delay. However, the vendor details will be shared with GS over the period of the time and till that time GS can reach out to HOOPP. Vendor contact details have been updated in the ADITLO.
A29: GS can add alert for Missing and Suspect Prices in case if there are any such case after price validation. Detailed requirements to finalized post go live.
A30: Other than this no other point pending at HOOPP side to be added to ADITLO. However if there is any question GS can reach out to us.
A31: HOOPP only wants to receive alerts for failed SLO scenarios. We don’t want any alert for successful run or alerts where SLO hasn’t reached. Please find below matrix for reference:
A34: Default Alerts:
A35: Failures, partial failures, informative alerts and general exception handling
A36: Full failures create alert
A37: HOOPP to define – failure, partial failure and information alerts
A38: Partial failure. Define the columns which we want full or partial failure
... A61: Will this be set up in soft go live?

Sheet Configured OMNI Alerts
A1: Alert Type | B1: Email Subject | C1: Action | D1: Description
A2: OMNI SLO Miss | B2: HOOPP:Prod:CRITICAL: OMNI SLO Miss | C2: Follow steps mentioned in the link | D2: This alert specifies if a particluar ODS job has not been completed and data for it has not moved to OMNI.
A3: OMNI PIPELINE Failure | B3: HOOPP:Prod:CRITICAL: OMNI PIPELINE Failure Notice | C3: Reach out MS Delivery team | D3: This alert specifies if the data ingestion into OMNI has failed and the reason for it. MS Delivery Team needs to be involved immediately once this alert is raised
A4: OMNI Data Discrepancy | B4: HOOPP:Prod:CRITICAL: OMNI DATASYNC Discrepancy | C4: Reach out MS Delivery team | D4: This alert specifies if there is any data discrepancy between ODS and OMNI.
